{
    "Name": "Great Scythe",
    "Description": "Weapon type: Halberd\nAttack type: Slash\n\nWeapon with a long curved blade. Converted\nfrom a wheat-harvesting tool.\n\nThe magnificent sharp curved blade\ninstills fear in opponents. Perhaps it is\ntheir survival instinct at work.",
    "ID": 1150000,
    "sortId": 1601,
    "weight": 5.0,
    "basicPrice": 200,
    "sellValue": 50,
    "fixPrice": 260,
    "req": {
        "Required Strength": 50.0,
        "Required Dexterity": 0.0,
        "Required Magic": 13.0,
        "Required Faith": 14.0
    },
    "scale": {
        "Strength Scaling": 13.0,
        "Dexterity Scaling": 85.0,
        "Intelligence Scaling": 0.0,
        "Faith Scaling": 0.0
    },
    "boolFlags": {
        "rightHandEquippable": true,
        "leftHandEquippable": true,
        "bothHandEquippable": true,
        "arrowSlotEquippable": false,
        "boltSlotEquippable": false,
        "enableGuard": true,
        "enableParry": false,
        "enableMagic": false,
        "enableSorcery": false,
        "enableMiracle": false,
        "enableVowMagic": false,
        "isNormalAttackType": false,
        "isBlowAttackType": false,
        "isSlashAttackType": true,
        "isThrustAttackType": false,
        "isEnhance": true,
        "isLuckCorrect": false,
        "isCustom": true,
        "disableBaseChangeReset": false,
        "disableRepair": false,
        "isDarkHand": false,
        "simpleModelForDlc": false,
        "lanternWep": false,
        "isVersusGhostWep": false,
        "isDragonSlayer": false,
        "isDeposit": true,
        "disableMultiDropShare": false
    },
    "behaviorVariationId": 5000,
    "wanderingEquipId": 1199000,
    "weaponWeightRate": 0.0,
    "phyGuardCutRate": 40.0,
    "magGuardCutRate": 10.0,
    "fireGuardCutRate": 30.0,
    "thunGuardCutRate": 30.0,
    "spEffectBehaviorId0": 6402,
    "spEffectBehaviorId1": -1,
    "spEffectBehaviorId2": -1,
    "residentSpEffectId": -1,
    "residentSpEffectId1": -1,
    "residentSpEffectId2": -1,
    "materialSetId": 0,
    "originEquipWep0": 1150000,
    "originEquipWep1": 1150000,
    "originEquipWep2": 1150000,
    "originEquipWep3": 1150000,
    "originEquipWep4": 1150000,
    "originEquipWep5": 1150000,
    "originEquipWep6": 1150005,
    "originEquipWep7": 1150005,
    "originEquipWep8": 1150005,
    "originEquipWep9": 1150005,
    "originEquipWep10": 1150005,
    "originEquipWep11": 1150010,
    "originEquipWep12": 1150010,
    "originEquipWep13": 1150010,
    "originEquipWep14": 1150010,
    "originEquipWep15": 1150010,
    "antiDemonDamageRate": 1.0,
    "antSaintDamageRate": 1.0,
    "antWeakA_DamageRate": 1.0,
    "antWeakB_DamageRate": 1.0,
    "vagrantItemLotId": 100700,
    "vagrantBonusEneDropItemLotId": 100710,
    "vagrantItemEneDropItemLotId": 100720,
    "equipModelId": 801,
    "iconId": 91,
    "durability": 130,
    "durabilityMax": 130,
    "attackThrowEscape": 1.0,
    "parryDamageLife": 10.0,
    "attackBasePhysics": 100.0,
    "attackBaseMagic": 0.0,
    "attackBaseFire": 0.0,
    "attackBaseThunder": 0.0,
    "attackBaseStamina": 25.0,
    "saWeaponDamage": 20.0,
    "saDurability": 0,
    "guardAngle": 0,
    "staminaGuardDef": 22,
    "reinforceTypeId": 0,
    "trophySGradeId": -1,
    "trophySeqId": 16,
    "throwAtkRate": 0.0,
    "bowDistRate": -1.0,
    "equipModelCategory": 7,
    "equipModelGender": 0,
    "weaponCategory": 7,
    "wepmotionCategory": 38,
    "guardmotionCategory": 2,
    "atkMaterial": 0,
    "defMaterial": 50,
    "defSfxMaterial": 50,
    "correctType": 0,
    "spAttribute": 1,
    "spAtkcategory": 50,
    "wepmotionOneHandId": 0,
    "wepmotionBothHandId": 13,
    "overStrength": 99.0,
    "attackBaseParry": 0.0,
    "defenseBaseParry": 0.0,
    "guardBaseRepel": 10.0,
    "attackBaseRepel": 40.0,
    "guardCutCancelRate": 0.0,
    "guardLevel": 2,
    "slashGuardCutRate": 0.0,
    "blowGuardCutRate": 0.0,
    "thrustGuardCutRate": 0.0,
    "poisonGuardResist": 36.0,
    "diseaseGuardResist": 36.0,
    "bloodGuardResist": 36.0,
    "curseGuardResist": 28.0,
    "isDurabilityDivergence": 0,
    "baseChangeCategory": 0,
    "pad_0": "System.Byte[]",
    "oldSortId": 1601,
    "pad_1": "System.Byte[]",
    "description": "Weapon type: Halberd\nAttack type: Slash\n\nWeapon with a long curved blade. Converted\nfrom a wheat-harvesting tool.\n\nThe magnificent sharp curved blade\ninstills fear in opponents. Perhaps it is\ntheir survival instinct at work.",
    "customData": {
        "whereToGet": "firelinkshrine",
        "slug": "Great-Scythe",
        "WeaponCategory": "Weapons",
        "WeaponType": "Slash",
        "image": "Great-Scythe.png"
    },
    "variants": [
        {
            "Name": "Great Scythe [Crystal]",
            "Description": "Weapon type: Halberd\nAttack type: Slash\n\nWeapon with a long curved blade. Converted\nfrom a wheat-harvesting tool.\n\nThe magnificent sharp curved blade\ninstills fear in opponents. Perhaps it is\ntheir survival instinct at work.",
            "ID": 1150100,
            "sortId": 1602,
            "weight": 5.0,
            "basicPrice": 200,
            "sellValue": 1,
            "fixPrice": 260,
            "req": {
                "Required Strength": 50.0,
                "Required Dexterity": 0.0,
                "Required Magic": 13.0,
                "Required Faith": 14.0
            },
            "scale": {
                "Strength Scaling": 13.0,
                "Dexterity Scaling": 85.0,
                "Intelligence Scaling": 0.0,
                "Faith Scaling": 0.0
            },
            "boolFlags": {
                "rightHandEquippable": true,
                "leftHandEquippable": true,
                "bothHandEquippable": true,
                "arrowSlotEquippable": false,
                "boltSlotEquippable": false,
                "enableGuard": true,
                "enableParry": false,
                "enableMagic": false,
                "enableSorcery": false,
                "enableMiracle": false,
                "enableVowMagic": false,
                "isNormalAttackType": false,
                "isBlowAttackType": false,
                "isSlashAttackType": true,
                "isThrustAttackType": false,
                "isEnhance": true,
                "isLuckCorrect": false,
                "isCustom": true,
                "disableBaseChangeReset": true,
                "disableRepair": true,
                "isDarkHand": false,
                "simpleModelForDlc": false,
                "lanternWep": false,
                "isVersusGhostWep": false,
                "isDragonSlayer": false,
                "isDeposit": true,
                "disableMultiDropShare": false
            },
            "behaviorVariationId": 5000,
            "wanderingEquipId": 1199000,
            "weaponWeightRate": 0.0,
            "phyGuardCutRate": 40.0,
            "magGuardCutRate": 10.0,
            "fireGuardCutRate": 30.0,
            "thunGuardCutRate": 30.0,
            "spEffectBehaviorId0": 6402,
            "spEffectBehaviorId1": -1,
            "spEffectBehaviorId2": -1,
            "residentSpEffectId": -1,
            "residentSpEffectId1": -1,
            "residentSpEffectId2": -1,
            "materialSetId": 100,
            "originEquipWep0": 1150010,
            "originEquipWep1": 1150010,
            "originEquipWep2": 1150010,
            "originEquipWep3": 1150010,
            "originEquipWep4": 1150010,
            "originEquipWep5": 1150010,
            "originEquipWep6": -1,
            "originEquipWep7": -1,
            "originEquipWep8": -1,
            "originEquipWep9": -1,
            "originEquipWep10": -1,
            "originEquipWep11": -1,
            "originEquipWep12": -1,
            "originEquipWep13": -1,
            "originEquipWep14": -1,
            "originEquipWep15": -1,
            "antiDemonDamageRate": 1.0,
            "antSaintDamageRate": 1.0,
            "antWeakA_DamageRate": 1.0,
            "antWeakB_DamageRate": 1.0,
            "vagrantItemLotId": 100700,
            "vagrantBonusEneDropItemLotId": 100710,
            "vagrantItemEneDropItemLotId": 100720,
            "equipModelId": 801,
            "iconId": 91,
            "durability": 13,
            "durabilityMax": 13,
            "attackThrowEscape": 1.0,
            "parryDamageLife": 10.0,
            "attackBasePhysics": 100.0,
            "attackBaseMagic": 0.0,
            "attackBaseFire": 0.0,
            "attackBaseThunder": 0.0,
            "attackBaseStamina": 25.0,
            "saWeaponDamage": 20.0,
            "saDurability": 0,
            "guardAngle": 0,
            "staminaGuardDef": 22,
            "reinforceTypeId": 100,
            "trophySGradeId": -1,
            "trophySeqId": 17,
            "throwAtkRate": 0.0,
            "bowDistRate": -1.0,
            "equipModelCategory": 7,
            "equipModelGender": 0,
            "weaponCategory": 7,
            "wepmotionCategory": 38,
            "guardmotionCategory": 2,
            "atkMaterial": 0,
            "defMaterial": 50,
            "defSfxMaterial": 50,
            "correctType": 0,
            "spAttribute": 1,
            "spAtkcategory": 50,
            "wepmotionOneHandId": 0,
            "wepmotionBothHandId": 13,
            "overStrength": 99.0,
            "attackBaseParry": 0.0,
            "defenseBaseParry": 0.0,
            "guardBaseRepel": 10.0,
            "attackBaseRepel": 40.0,
            "guardCutCancelRate": 0.0,
            "guardLevel": 2,
            "slashGuardCutRate": 0.0,
            "blowGuardCutRate": 0.0,
            "thrustGuardCutRate": 0.0,
            "poisonGuardResist": 36.0,
            "diseaseGuardResist": 36.0,
            "bloodGuardResist": 36.0,
            "curseGuardResist": 28.0,
            "isDurabilityDivergence": 0,
            "baseChangeCategory": 5,
            "pad_0": "System.Byte[]",
            "oldSortId": 1602,
            "pad_1": "System.Byte[]",
            "description": "Weapon type: Halberd\nAttack type: Slash\n\nWeapon with a long curved blade. Converted\nfrom a wheat-harvesting tool.\n\nThe magnificent sharp curved blade\ninstills fear in opponents. Perhaps it is\ntheir survival instinct at work.",
            "customData": {
                "whereToGet": "firelinkshrine",
                "slug": "Great-Scythe-[Crystal]",
                "WeaponCategory": "Unknown",
                "WeaponType": "Slash",
                "image": "Great-Scythe-[Crystal].png"
            }
        },
        {
            "Name": "Great Scythe [Lightning]",
            "Description": "Weapon type: Halberd\nAttack type: Slash\n\nWeapon with a long curved blade. Converted\nfrom a wheat-harvesting tool.\n\nThe magnificent sharp curved blade\ninstills fear in opponents. Perhaps it is\ntheir survival instinct at work.",
            "ID": 1150200,
            "sortId": 1603,
            "weight": 5.0,
            "basicPrice": 200,
            "sellValue": 500,
            "fixPrice": 260,
            "req": {
                "Required Strength": 50.0,
                "Required Dexterity": 0.0,
                "Required Magic": 13.0,
                "Required Faith": 14.0
            },
            "scale": {
                "Strength Scaling": 0.0,
                "Dexterity Scaling": 0.0,
                "Intelligence Scaling": 0.0,
                "Faith Scaling": 0.0
            },
            "boolFlags": {
                "rightHandEquippable": true,
                "leftHandEquippable": true,
                "bothHandEquippable": true,
                "arrowSlotEquippable": false,
                "boltSlotEquippable": false,
                "enableGuard": true,
                "enableParry": false,
                "enableMagic": false,
                "enableSorcery": false,
                "enableMiracle": false,
                "enableVowMagic": false,
                "isNormalAttackType": false,
                "isBlowAttackType": false,
                "isSlashAttackType": true,
                "isThrustAttackType": false,
                "isEnhance": false,
                "isLuckCorrect": false,
                "isCustom": true,
                "disableBaseChangeReset": false,
                "disableRepair": false,
                "isDarkHand": false,
                "simpleModelForDlc": false,
                "lanternWep": false,
                "isVersusGhostWep": false,
                "isDragonSlayer": false,
                "isDeposit": true,
                "disableMultiDropShare": false
            },
            "behaviorVariationId": 5000,
            "wanderingEquipId": 1199000,
            "weaponWeightRate": 0.0,
            "phyGuardCutRate": 40.0,
            "magGuardCutRate": 10.0,
            "fireGuardCutRate": 30.0,
            "thunGuardCutRate": 30.0,
            "spEffectBehaviorId0": 6402,
            "spEffectBehaviorId1": -1,
            "spEffectBehaviorId2": -1,
            "residentSpEffectId": -1,
            "residentSpEffectId1": -1,
            "residentSpEffectId2": -1,
            "materialSetId": 200,
            "originEquipWep0": 1150010,
            "originEquipWep1": 1150010,
            "originEquipWep2": 1150010,
            "originEquipWep3": 1150010,
            "originEquipWep4": 1150010,
            "originEquipWep5": 1150010,
            "originEquipWep6": -1,
            "originEquipWep7": -1,
            "originEquipWep8": -1,
            "originEquipWep9": -1,
            "originEquipWep10": -1,
            "originEquipWep11": -1,
            "originEquipWep12": -1,
            "originEquipWep13": -1,
            "originEquipWep14": -1,
            "originEquipWep15": -1,
            "antiDemonDamageRate": 1.0,
            "antSaintDamageRate": 1.0,
            "antWeakA_DamageRate": 1.0,
            "antWeakB_DamageRate": 1.0,
            "vagrantItemLotId": 100700,
            "vagrantBonusEneDropItemLotId": 100710,
            "vagrantItemEneDropItemLotId": 100720,
            "equipModelId": 801,
            "iconId": 91,
            "durability": 130,
            "durabilityMax": 130,
            "attackThrowEscape": 1.0,
            "parryDamageLife": 10.0,
            "attackBasePhysics": 100.0,
            "attackBaseMagic": 0.0,
            "attackBaseFire": 0.0,
            "attackBaseThunder": 100.0,
            "attackBaseStamina": 25.0,
            "saWeaponDamage": 20.0,
            "saDurability": 0,
            "guardAngle": 0,
            "staminaGuardDef": 22,
            "reinforceTypeId": 200,
            "trophySGradeId": -1,
            "trophySeqId": 18,
            "throwAtkRate": 0.0,
            "bowDistRate": -1.0,
            "equipModelCategory": 7,
            "equipModelGender": 0,
            "weaponCategory": 7,
            "wepmotionCategory": 38,
            "guardmotionCategory": 2,
            "atkMaterial": 0,
            "defMaterial": 50,
            "defSfxMaterial": 50,
            "correctType": 0,
            "spAttribute": 6,
            "spAtkcategory": 50,
            "wepmotionOneHandId": 0,
            "wepmotionBothHandId": 13,
            "overStrength": 99.0,
            "attackBaseParry": 0.0,
            "defenseBaseParry": 0.0,
            "guardBaseRepel": 10.0,
            "attackBaseRepel": 40.0,
            "guardCutCancelRate": 0.0,
            "guardLevel": 2,
            "slashGuardCutRate": 0.0,
            "blowGuardCutRate": 0.0,
            "thrustGuardCutRate": 0.0,
            "poisonGuardResist": 36.0,
            "diseaseGuardResist": 36.0,
            "bloodGuardResist": 36.0,
            "curseGuardResist": 28.0,
            "isDurabilityDivergence": 0,
            "baseChangeCategory": 10,
            "pad_0": "System.Byte[]",
            "oldSortId": 1603,
            "pad_1": "System.Byte[]",
            "description": "Weapon type: Halberd\nAttack type: Slash\n\nWeapon with a long curved blade. Converted\nfrom a wheat-harvesting tool.\n\nThe magnificent sharp curved blade\ninstills fear in opponents. Perhaps it is\ntheir survival instinct at work.",
            "customData": {
                "whereToGet": "firelinkshrine",
                "slug": "Great-Scythe-[Lightning]",
                "WeaponCategory": "Unknown",
                "WeaponType": "Slash",
                "image": "Great-Scythe-[Lightning].png"
            }
        },
        {
            "Name": "Great Scythe [Raw]",
            "Description": "Weapon type: Halberd\nAttack type: Slash\n\nWeapon with a long curved blade. Converted\nfrom a wheat-harvesting tool.\n\nThe magnificent sharp curved blade\ninstills fear in opponents. Perhaps it is\ntheir survival instinct at work.",
            "ID": 1150300,
            "sortId": 1604,
            "weight": 5.0,
            "basicPrice": 200,
            "sellValue": 50,
            "fixPrice": 260,
            "req": {
                "Required Strength": 50.0,
                "Required Dexterity": 0.0,
                "Required Magic": 13.0,
                "Required Faith": 14.0
            },
            "scale": {
                "Strength Scaling": 10.0,
                "Dexterity Scaling": 64.0,
                "Intelligence Scaling": 0.0,
                "Faith Scaling": 0.0
            },
            "boolFlags": {
                "rightHandEquippable": true,
                "leftHandEquippable": true,
                "bothHandEquippable": true,
                "arrowSlotEquippable": false,
                "boltSlotEquippable": false,
                "enableGuard": true,
                "enableParry": false,
                "enableMagic": false,
                "enableSorcery": false,
                "enableMiracle": false,
                "enableVowMagic": false,
                "isNormalAttackType": false,
                "isBlowAttackType": false,
                "isSlashAttackType": true,
                "isThrustAttackType": false,
                "isEnhance": true,
                "isLuckCorrect": false,
                "isCustom": true,
                "disableBaseChangeReset": false,
                "disableRepair": false,
                "isDarkHand": false,
                "simpleModelForDlc": false,
                "lanternWep": false,
                "isVersusGhostWep": false,
                "isDragonSlayer": false,
                "isDeposit": true,
                "disableMultiDropShare": false
            },
            "behaviorVariationId": 5000,
            "wanderingEquipId": 1199000,
            "weaponWeightRate": 0.0,
            "phyGuardCutRate": 40.0,
            "magGuardCutRate": 10.0,
            "fireGuardCutRate": 30.0,
            "thunGuardCutRate": 30.0,
            "spEffectBehaviorId0": 6402,
            "spEffectBehaviorId1": -1,
            "spEffectBehaviorId2": -1,
            "residentSpEffectId": -1,
            "residentSpEffectId1": -1,
            "residentSpEffectId2": -1,
            "materialSetId": 300,
            "originEquipWep0": 1150005,
            "originEquipWep1": 1150005,
            "originEquipWep2": 1150005,
            "originEquipWep3": 1150005,
            "originEquipWep4": 1150005,
            "originEquipWep5": 1150005,
            "originEquipWep6": -1,
            "originEquipWep7": -1,
            "originEquipWep8": -1,
            "originEquipWep9": -1,
            "originEquipWep10": -1,
            "originEquipWep11": -1,
            "originEquipWep12": -1,
            "originEquipWep13": -1,
            "originEquipWep14": -1,
            "originEquipWep15": -1,
            "antiDemonDamageRate": 1.0,
            "antSaintDamageRate": 1.0,
            "antWeakA_DamageRate": 1.0,
            "antWeakB_DamageRate": 1.0,
            "vagrantItemLotId": -1,
            "vagrantBonusEneDropItemLotId": -1,
            "vagrantItemEneDropItemLotId": -1,
            "equipModelId": 801,
            "iconId": 91,
            "durability": 130,
            "durabilityMax": 130,
            "attackThrowEscape": 1.0,
            "parryDamageLife": 10.0,
            "attackBasePhysics": 115.0,
            "attackBaseMagic": 0.0,
            "attackBaseFire": 0.0,
            "attackBaseThunder": 0.0,
            "attackBaseStamina": 25.0,
            "saWeaponDamage": 20.0,
            "saDurability": 0,
            "guardAngle": 0,
            "staminaGuardDef": 22,
            "reinforceTypeId": 300,
            "trophySGradeId": -1,
            "trophySeqId": 19,
            "throwAtkRate": 0.0,
            "bowDistRate": -1.0,
            "equipModelCategory": 7,
            "equipModelGender": 0,
            "weaponCategory": 7,
            "wepmotionCategory": 38,
            "guardmotionCategory": 2,
            "atkMaterial": 0,
            "defMaterial": 50,
            "defSfxMaterial": 50,
            "correctType": 0,
            "spAttribute": 1,
            "spAtkcategory": 50,
            "wepmotionOneHandId": 0,
            "wepmotionBothHandId": 13,
            "overStrength": 99.0,
            "attackBaseParry": 0.0,
            "defenseBaseParry": 0.0,
            "guardBaseRepel": 10.0,
            "attackBaseRepel": 40.0,
            "guardCutCancelRate": 0.0,
            "guardLevel": 2,
            "slashGuardCutRate": 0.0,
            "blowGuardCutRate": 0.0,
            "thrustGuardCutRate": 0.0,
            "poisonGuardResist": 36.0,
            "diseaseGuardResist": 36.0,
            "bloodGuardResist": 36.0,
            "curseGuardResist": 28.0,
            "isDurabilityDivergence": 0,
            "baseChangeCategory": 15,
            "pad_0": "System.Byte[]",
            "oldSortId": 1604,
            "pad_1": "System.Byte[]",
            "description": "Weapon type: Halberd\nAttack type: Slash\n\nWeapon with a long curved blade. Converted\nfrom a wheat-harvesting tool.\n\nThe magnificent sharp curved blade\ninstills fear in opponents. Perhaps it is\ntheir survival instinct at work.",
            "customData": {
                "whereToGet": "firelinkshrine",
                "slug": "Great-Scythe-[Raw]",
                "WeaponCategory": "Unknown",
                "WeaponType": "Slash",
                "image": "Great-Scythe-[Raw].png"
            }
        },
        {
            "Name": "Great Scythe [Magic]",
            "Description": "Weapon type: Halberd\nAttack type: Slash\n\nWeapon with a long curved blade. Converted\nfrom a wheat-harvesting tool.\n\nThe magnificent sharp curved blade\ninstills fear in opponents. Perhaps it is\ntheir survival instinct at work.",
            "ID": 1150400,
            "sortId": 1605,
            "weight": 5.0,
            "basicPrice": 200,
            "sellValue": 50,
            "fixPrice": 260,
            "req": {
                "Required Strength": 50.0,
                "Required Dexterity": 0.0,
                "Required Magic": 13.0,
                "Required Faith": 14.0
            },
            "scale": {
                "Strength Scaling": 4.0,
                "Dexterity Scaling": 24.0,
                "Intelligence Scaling": 71.0,
                "Faith Scaling": 0.0
            },
            "boolFlags": {
                "rightHandEquippable": true,
                "leftHandEquippable": true,
                "bothHandEquippable": true,
                "arrowSlotEquippable": false,
                "boltSlotEquippable": false,
                "enableGuard": true,
                "enableParry": false,
                "enableMagic": false,
                "enableSorcery": false,
                "enableMiracle": false,
                "enableVowMagic": false,
                "isNormalAttackType": false,
                "isBlowAttackType": false,
                "isSlashAttackType": true,
                "isThrustAttackType": false,
                "isEnhance": false,
                "isLuckCorrect": false,
                "isCustom": true,
                "disableBaseChangeReset": false,
                "disableRepair": false,
                "isDarkHand": false,
                "simpleModelForDlc": false,
                "lanternWep": false,
                "isVersusGhostWep": false,
                "isDragonSlayer": false,
                "isDeposit": true,
                "disableMultiDropShare": false
            },
            "behaviorVariationId": 5000,
            "wanderingEquipId": 1199000,
            "weaponWeightRate": 0.0,
            "phyGuardCutRate": 40.0,
            "magGuardCutRate": 10.0,
            "fireGuardCutRate": 30.0,
            "thunGuardCutRate": 30.0,
            "spEffectBehaviorId0": 6402,
            "spEffectBehaviorId1": -1,
            "spEffectBehaviorId2": -1,
            "residentSpEffectId": -1,
            "residentSpEffectId1": -1,
            "residentSpEffectId2": -1,
            "materialSetId": 400,
            "originEquipWep0": 1150005,
            "originEquipWep1": 1150005,
            "originEquipWep2": 1150005,
            "originEquipWep3": 1150005,
            "originEquipWep4": 1150005,
            "originEquipWep5": 1150005,
            "originEquipWep6": 1150405,
            "originEquipWep7": 1150405,
            "originEquipWep8": 1150405,
            "originEquipWep9": 1150405,
            "originEquipWep10": 1150405,
            "originEquipWep11": -1,
            "originEquipWep12": -1,
            "originEquipWep13": -1,
            "originEquipWep14": -1,
            "originEquipWep15": -1,
            "antiDemonDamageRate": 1.0,
            "antSaintDamageRate": 1.0,
            "antWeakA_DamageRate": 1.0,
            "antWeakB_DamageRate": 1.0,
            "vagrantItemLotId": 100800,
            "vagrantBonusEneDropItemLotId": 100810,
            "vagrantItemEneDropItemLotId": 100820,
            "equipModelId": 801,
            "iconId": 91,
            "durability": 130,
            "durabilityMax": 130,
            "attackThrowEscape": 1.0,
            "parryDamageLife": 10.0,
            "attackBasePhysics": 75.0,
            "attackBaseMagic": 81.0,
            "attackBaseFire": 0.0,
            "attackBaseThunder": 0.0,
            "attackBaseStamina": 25.0,
            "saWeaponDamage": 20.0,
            "saDurability": 0,
            "guardAngle": 0,
            "staminaGuardDef": 22,
            "reinforceTypeId": 400,
            "trophySGradeId": -1,
            "trophySeqId": 20,
            "throwAtkRate": 0.0,
            "bowDistRate": -1.0,
            "equipModelCategory": 7,
            "equipModelGender": 0,
            "weaponCategory": 7,
            "wepmotionCategory": 38,
            "guardmotionCategory": 2,
            "atkMaterial": 0,
            "defMaterial": 50,
            "defSfxMaterial": 50,
            "correctType": 1,
            "spAttribute": 1,
            "spAtkcategory": 50,
            "wepmotionOneHandId": 0,
            "wepmotionBothHandId": 13,
            "overStrength": 99.0,
            "attackBaseParry": 0.0,
            "defenseBaseParry": 0.0,
            "guardBaseRepel": 10.0,
            "attackBaseRepel": 40.0,
            "guardCutCancelRate": 0.0,
            "guardLevel": 2,
            "slashGuardCutRate": 0.0,
            "blowGuardCutRate": 0.0,
            "thrustGuardCutRate": 0.0,
            "poisonGuardResist": 36.0,
            "diseaseGuardResist": 36.0,
            "bloodGuardResist": 36.0,
            "curseGuardResist": 28.0,
            "isDurabilityDivergence": 0,
            "baseChangeCategory": 20,
            "pad_0": "System.Byte[]",
            "oldSortId": 1605,
            "pad_1": "System.Byte[]",
            "description": "Weapon type: Halberd\nAttack type: Slash\n\nWeapon with a long curved blade. Converted\nfrom a wheat-harvesting tool.\n\nThe magnificent sharp curved blade\ninstills fear in opponents. Perhaps it is\ntheir survival instinct at work.",
            "customData": {
                "whereToGet": "firelinkshrine",
                "slug": "Great-Scythe-[Magic]",
                "WeaponCategory": "Unknown",
                "WeaponType": "Slash",
                "image": "Great-Scythe-[Magic].png"
            }
        },
        {
            "Name": "Great Scythe [Enchanted]",
            "Description": "Weapon type: Halberd\nAttack type: Slash\n\nWeapon with a long curved blade. Converted\nfrom a wheat-harvesting tool.\n\nThe magnificent sharp curved blade\ninstills fear in opponents. Perhaps it is\ntheir survival instinct at work.",
            "ID": 1150500,
            "sortId": 1606,
            "weight": 5.0,
            "basicPrice": 200,
            "sellValue": 50,
            "fixPrice": 260,
            "req": {
                "Required Strength": 50.0,
                "Required Dexterity": 0.0,
                "Required Magic": 13.0,
                "Required Faith": 14.0
            },
            "scale": {
                "Strength Scaling": 3.0,
                "Dexterity Scaling": 17.0,
                "Intelligence Scaling": 69.0,
                "Faith Scaling": 0.0
            },
            "boolFlags": {
                "rightHandEquippable": true,
                "leftHandEquippable": true,
                "bothHandEquippable": true,
                "arrowSlotEquippable": false,
                "boltSlotEquippable": false,
                "enableGuard": true,
                "enableParry": false,
                "enableMagic": false,
                "enableSorcery": false,
                "enableMiracle": false,
                "enableVowMagic": false,
                "isNormalAttackType": false,
                "isBlowAttackType": false,
                "isSlashAttackType": true,
                "isThrustAttackType": false,
                "isEnhance": false,
                "isLuckCorrect": false,
                "isCustom": true,
                "disableBaseChangeReset": false,
                "disableRepair": false,
                "isDarkHand": false,
                "simpleModelForDlc": false,
                "lanternWep": false,
                "isVersusGhostWep": false,
                "isDragonSlayer": false,
                "isDeposit": true,
                "disableMultiDropShare": false
            },
            "behaviorVariationId": 5000,
            "wanderingEquipId": 1199000,
            "weaponWeightRate": 0.0,
            "phyGuardCutRate": 40.0,
            "magGuardCutRate": 10.0,
            "fireGuardCutRate": 30.0,
            "thunGuardCutRate": 30.0,
            "spEffectBehaviorId0": 6402,
            "spEffectBehaviorId1": -1,
            "spEffectBehaviorId2": -1,
            "residentSpEffectId": -1,
            "residentSpEffectId1": -1,
            "residentSpEffectId2": -1,
            "materialSetId": 500,
            "originEquipWep0": 1150405,
            "originEquipWep1": 1150405,
            "originEquipWep2": 1150405,
            "originEquipWep3": 1150405,
            "originEquipWep4": 1150405,
            "originEquipWep5": 1150405,
            "originEquipWep6": -1,
            "originEquipWep7": -1,
            "originEquipWep8": -1,
            "originEquipWep9": -1,
            "originEquipWep10": -1,
            "originEquipWep11": -1,
            "originEquipWep12": -1,
            "originEquipWep13": -1,
            "originEquipWep14": -1,
            "originEquipWep15": -1,
            "antiDemonDamageRate": 1.0,
            "antSaintDamageRate": 1.0,
            "antWeakA_DamageRate": 1.0,
            "antWeakB_DamageRate": 1.0,
            "vagrantItemLotId": 100800,
            "vagrantBonusEneDropItemLotId": 100810,
            "vagrantItemEneDropItemLotId": 100820,
            "equipModelId": 801,
            "iconId": 91,
            "durability": 130,
            "durabilityMax": 130,
            "attackThrowEscape": 1.0,
            "parryDamageLife": 10.0,
            "attackBasePhysics": 75.0,
            "attackBaseMagic": 80.0,
            "attackBaseFire": 0.0,
            "attackBaseThunder": 0.0,
            "attackBaseStamina": 25.0,
            "saWeaponDamage": 20.0,
            "saDurability": 0,
            "guardAngle": 0,
            "staminaGuardDef": 22,
            "reinforceTypeId": 500,
            "trophySGradeId": -1,
            "trophySeqId": 21,
            "throwAtkRate": 0.0,
            "bowDistRate": -1.0,
            "equipModelCategory": 7,
            "equipModelGender": 0,
            "weaponCategory": 7,
            "wepmotionCategory": 38,
            "guardmotionCategory": 2,
            "atkMaterial": 0,
            "defMaterial": 50,
            "defSfxMaterial": 50,
            "correctType": 1,
            "spAttribute": 1,
            "spAtkcategory": 50,
            "wepmotionOneHandId": 0,
            "wepmotionBothHandId": 13,
            "overStrength": 99.0,
            "attackBaseParry": 0.0,
            "defenseBaseParry": 0.0,
            "guardBaseRepel": 10.0,
            "attackBaseRepel": 40.0,
            "guardCutCancelRate": 0.0,
            "guardLevel": 2,
            "slashGuardCutRate": 0.0,
            "blowGuardCutRate": 0.0,
            "thrustGuardCutRate": 0.0,
            "poisonGuardResist": 36.0,
            "diseaseGuardResist": 36.0,
            "bloodGuardResist": 36.0,
            "curseGuardResist": 28.0,
            "isDurabilityDivergence": 0,
            "baseChangeCategory": 22,
            "pad_0": "System.Byte[]",
            "oldSortId": 1606,
            "pad_1": "System.Byte[]",
            "description": "Weapon type: Halberd\nAttack type: Slash\n\nWeapon with a long curved blade. Converted\nfrom a wheat-harvesting tool.\n\nThe magnificent sharp curved blade\ninstills fear in opponents. Perhaps it is\ntheir survival instinct at work.",
            "customData": {
                "whereToGet": "firelinkshrine",
                "slug": "Great-Scythe-[Enchanted]",
                "WeaponCategory": "Unknown",
                "WeaponType": "Slash",
                "image": "Great-Scythe-[Enchanted].png"
            }
        },
        {
            "Name": "Great Scythe [Divine]",
            "Description": "Weapon type: Halberd\nAttack type: Slash\n\nWeapon with a long curved blade. Converted\nfrom a wheat-harvesting tool.\n\nThe magnificent sharp curved blade\ninstills fear in opponents. Perhaps it is\ntheir survival instinct at work.",
            "ID": 1150600,
            "sortId": 1607,
            "weight": 5.0,
            "basicPrice": 200,
            "sellValue": 100,
            "fixPrice": 260,
            "req": {
                "Required Strength": 50.0,
                "Required Dexterity": 0.0,
                "Required Magic": 13.0,
                "Required Faith": 14.0
            },
            "scale": {
                "Strength Scaling": 5.0,
                "Dexterity Scaling": 33.0,
                "Intelligence Scaling": 0.0,
                "Faith Scaling": 70.0
            },
            "boolFlags": {
                "rightHandEquippable": true,
                "leftHandEquippable": true,
                "bothHandEquippable": true,
                "arrowSlotEquippable": false,
                "boltSlotEquippable": false,
                "enableGuard": true,
                "enableParry": false,
                "enableMagic": false,
                "enableSorcery": false,
                "enableMiracle": false,
                "enableVowMagic": false,
                "isNormalAttackType": false,
                "isBlowAttackType": false,
                "isSlashAttackType": true,
                "isThrustAttackType": false,
                "isEnhance": false,
                "isLuckCorrect": false,
                "isCustom": true,
                "disableBaseChangeReset": false,
                "disableRepair": false,
                "isDarkHand": false,
                "simpleModelForDlc": false,
                "lanternWep": false,
                "isVersusGhostWep": false,
                "isDragonSlayer": false,
                "isDeposit": true,
                "disableMultiDropShare": false
            },
            "behaviorVariationId": 5000,
            "wanderingEquipId": 1199000,
            "weaponWeightRate": 0.0,
            "phyGuardCutRate": 40.0,
            "magGuardCutRate": 10.0,
            "fireGuardCutRate": 30.0,
            "thunGuardCutRate": 30.0,
            "spEffectBehaviorId0": 6402,
            "spEffectBehaviorId1": -1,
            "spEffectBehaviorId2": -1,
            "residentSpEffectId": -1,
            "residentSpEffectId1": -1,
            "residentSpEffectId2": -1,
            "materialSetId": 600,
            "originEquipWep0": 1150005,
            "originEquipWep1": 1150005,
            "originEquipWep2": 1150005,
            "originEquipWep3": 1150005,
            "originEquipWep4": 1150005,
            "originEquipWep5": 1150005,
            "originEquipWep6": 1150605,
            "originEquipWep7": 1150605,
            "originEquipWep8": 1150605,
            "originEquipWep9": 1150605,
            "originEquipWep10": 1150605,
            "originEquipWep11": -1,
            "originEquipWep12": -1,
            "originEquipWep13": -1,
            "originEquipWep14": -1,
            "originEquipWep15": -1,
            "antiDemonDamageRate": 1.0,
            "antSaintDamageRate": 1.1,
            "antWeakA_DamageRate": 1.0,
            "antWeakB_DamageRate": 1.0,
            "vagrantItemLotId": 100900,
            "vagrantBonusEneDropItemLotId": 100910,
            "vagrantItemEneDropItemLotId": 100920,
            "equipModelId": 801,
            "iconId": 91,
            "durability": 130,
            "durabilityMax": 130,
            "attackThrowEscape": 1.0,
            "parryDamageLife": 10.0,
            "attackBasePhysics": 68.0,
            "attackBaseMagic": 83.0,
            "attackBaseFire": 0.0,
            "attackBaseThunder": 0.0,
            "attackBaseStamina": 25.0,
            "saWeaponDamage": 20.0,
            "saDurability": 0,
            "guardAngle": 0,
            "staminaGuardDef": 22,
            "reinforceTypeId": 600,
            "trophySGradeId": -1,
            "trophySeqId": 22,
            "throwAtkRate": 0.0,
            "bowDistRate": -1.0,
            "equipModelCategory": 7,
            "equipModelGender": 0,
            "weaponCategory": 7,
            "wepmotionCategory": 38,
            "guardmotionCategory": 2,
            "atkMaterial": 0,
            "defMaterial": 50,
            "defSfxMaterial": 50,
            "correctType": 1,
            "spAttribute": 1,
            "spAtkcategory": 50,
            "wepmotionOneHandId": 0,
            "wepmotionBothHandId": 13,
            "overStrength": 99.0,
            "attackBaseParry": 0.0,
            "defenseBaseParry": 0.0,
            "guardBaseRepel": 10.0,
            "attackBaseRepel": 40.0,
            "guardCutCancelRate": 0.0,
            "guardLevel": 2,
            "slashGuardCutRate": 0.0,
            "blowGuardCutRate": 0.0,
            "thrustGuardCutRate": 0.0,
            "poisonGuardResist": 36.0,
            "diseaseGuardResist": 36.0,
            "bloodGuardResist": 36.0,
            "curseGuardResist": 28.0,
            "isDurabilityDivergence": 0,
            "baseChangeCategory": 25,
            "pad_0": "System.Byte[]",
            "oldSortId": 1607,
            "pad_1": "System.Byte[]",
            "description": "Weapon type: Halberd\nAttack type: Slash\n\nWeapon with a long curved blade. Converted\nfrom a wheat-harvesting tool.\n\nThe magnificent sharp curved blade\ninstills fear in opponents. Perhaps it is\ntheir survival instinct at work.",
            "customData": {
                "whereToGet": "firelinkshrine",
                "slug": "Great-Scythe-[Divine]",
                "WeaponCategory": "Unknown",
                "WeaponType": "Slash",
                "image": "Great-Scythe-[Divine].png"
            }
        },
        {
            "Name": "Great Scythe [Occult]",
            "Description": "Weapon type: Halberd\nAttack type: Slash\n\nWeapon with a long curved blade. Converted\nfrom a wheat-harvesting tool.\n\nThe magnificent sharp curved blade\ninstills fear in opponents. Perhaps it is\ntheir survival instinct at work.",
            "ID": 1150700,
            "sortId": 1608,
            "weight": 5.0,
            "basicPrice": 200,
            "sellValue": 100,
            "fixPrice": 260,
            "req": {
                "Required Strength": 50.0,
                "Required Dexterity": 0.0,
                "Required Magic": 13.0,
                "Required Faith": 14.0
            },
            "scale": {
                "Strength Scaling": 5.0,
                "Dexterity Scaling": 31.0,
                "Intelligence Scaling": 0.0,
                "Faith Scaling": 82.0
            },
            "boolFlags": {
                "rightHandEquippable": true,
                "leftHandEquippable": true,
                "bothHandEquippable": true,
                "arrowSlotEquippable": false,
                "boltSlotEquippable": false,
                "enableGuard": true,
                "enableParry": false,
                "enableMagic": false,
                "enableSorcery": false,
                "enableMiracle": false,
                "enableVowMagic": false,
                "isNormalAttackType": false,
                "isBlowAttackType": false,
                "isSlashAttackType": true,
                "isThrustAttackType": false,
                "isEnhance": false,
                "isLuckCorrect": false,
                "isCustom": true,
                "disableBaseChangeReset": false,
                "disableRepair": false,
                "isDarkHand": false,
                "simpleModelForDlc": false,
                "lanternWep": false,
                "isVersusGhostWep": false,
                "isDragonSlayer": false,
                "isDeposit": true,
                "disableMultiDropShare": false
            },
            "behaviorVariationId": 5000,
            "wanderingEquipId": 1199000,
            "weaponWeightRate": 0.0,
            "phyGuardCutRate": 40.0,
            "magGuardCutRate": 10.0,
            "fireGuardCutRate": 30.0,
            "thunGuardCutRate": 30.0,
            "spEffectBehaviorId0": 6402,
            "spEffectBehaviorId1": -1,
            "spEffectBehaviorId2": -1,
            "residentSpEffectId": -1,
            "residentSpEffectId1": -1,
            "residentSpEffectId2": -1,
            "materialSetId": 700,
            "originEquipWep0": 1150605,
            "originEquipWep1": 1150605,
            "originEquipWep2": 1150605,
            "originEquipWep3": 1150605,
            "originEquipWep4": 1150605,
            "originEquipWep5": 1150605,
            "originEquipWep6": -1,
            "originEquipWep7": -1,
            "originEquipWep8": -1,
            "originEquipWep9": -1,
            "originEquipWep10": -1,
            "originEquipWep11": -1,
            "originEquipWep12": -1,
            "originEquipWep13": -1,
            "originEquipWep14": -1,
            "originEquipWep15": -1,
            "antiDemonDamageRate": 1.0,
            "antSaintDamageRate": 1.0,
            "antWeakA_DamageRate": 1.1,
            "antWeakB_DamageRate": 1.0,
            "vagrantItemLotId": 100900,
            "vagrantBonusEneDropItemLotId": 100910,
            "vagrantItemEneDropItemLotId": 100920,
            "equipModelId": 801,
            "iconId": 91,
            "durability": 130,
            "durabilityMax": 130,
            "attackThrowEscape": 1.0,
            "parryDamageLife": 10.0,
            "attackBasePhysics": 69.0,
            "attackBaseMagic": 75.0,
            "attackBaseFire": 0.0,
            "attackBaseThunder": 0.0,
            "attackBaseStamina": 25.0,
            "saWeaponDamage": 20.0,
            "saDurability": 0,
            "guardAngle": 0,
            "staminaGuardDef": 22,
            "reinforceTypeId": 700,
            "trophySGradeId": -1,
            "trophySeqId": 23,
            "throwAtkRate": 0.0,
            "bowDistRate": -1.0,
            "equipModelCategory": 7,
            "equipModelGender": 0,
            "weaponCategory": 7,
            "wepmotionCategory": 38,
            "guardmotionCategory": 2,
            "atkMaterial": 0,
            "defMaterial": 50,
            "defSfxMaterial": 50,
            "correctType": 1,
            "spAttribute": 1,
            "spAtkcategory": 50,
            "wepmotionOneHandId": 0,
            "wepmotionBothHandId": 13,
            "overStrength": 99.0,
            "attackBaseParry": 0.0,
            "defenseBaseParry": 0.0,
            "guardBaseRepel": 10.0,
            "attackBaseRepel": 40.0,
            "guardCutCancelRate": 0.0,
            "guardLevel": 2,
            "slashGuardCutRate": 0.0,
            "blowGuardCutRate": 0.0,
            "thrustGuardCutRate": 0.0,
            "poisonGuardResist": 36.0,
            "diseaseGuardResist": 36.0,
            "bloodGuardResist": 36.0,
            "curseGuardResist": 28.0,
            "isDurabilityDivergence": 0,
            "baseChangeCategory": 30,
            "pad_0": "System.Byte[]",
            "oldSortId": 1608,
            "pad_1": "System.Byte[]",
            "description": "Weapon type: Halberd\nAttack type: Slash\n\nWeapon with a long curved blade. Converted\nfrom a wheat-harvesting tool.\n\nThe magnificent sharp curved blade\ninstills fear in opponents. Perhaps it is\ntheir survival instinct at work.",
            "customData": {
                "whereToGet": "firelinkshrine",
                "slug": "Great-Scythe-[Occult]",
                "WeaponCategory": "Unknown",
                "WeaponType": "Slash",
                "image": "Great-Scythe-[Occult].png"
            }
        },
        {
            "Name": "Great Scythe [Fire]",
            "Description": "Weapon type: Halberd\nAttack type: Slash\n\nWeapon with a long curved blade. Converted\nfrom a wheat-harvesting tool.\n\nThe magnificent sharp curved blade\ninstills fear in opponents. Perhaps it is\ntheir survival instinct at work.",
            "ID": 1150800,
            "sortId": 1609,
            "weight": 5.0,
            "basicPrice": 200,
            "sellValue": 50,
            "fixPrice": 260,
            "req": {
                "Required Strength": 50.0,
                "Required Dexterity": 0.0,
                "Required Magic": 13.0,
                "Required Faith": 14.0
            },
            "scale": {
                "Strength Scaling": 0.0,
                "Dexterity Scaling": 0.0,
                "Intelligence Scaling": 0.0,
                "Faith Scaling": 0.0
            },
            "boolFlags": {
                "rightHandEquippable": true,
                "leftHandEquippable": true,
                "bothHandEquippable": true,
                "arrowSlotEquippable": false,
                "boltSlotEquippable": false,
                "enableGuard": true,
                "enableParry": false,
                "enableMagic": false,
                "enableSorcery": false,
                "enableMiracle": false,
                "enableVowMagic": false,
                "isNormalAttackType": false,
                "isBlowAttackType": false,
                "isSlashAttackType": true,
                "isThrustAttackType": false,
                "isEnhance": false,
                "isLuckCorrect": false,
                "isCustom": true,
                "disableBaseChangeReset": false,
                "disableRepair": false,
                "isDarkHand": false,
                "simpleModelForDlc": false,
                "lanternWep": false,
                "isVersusGhostWep": false,
                "isDragonSlayer": false,
                "isDeposit": true,
                "disableMultiDropShare": false
            },
            "behaviorVariationId": 5000,
            "wanderingEquipId": 1199000,
            "weaponWeightRate": 0.0,
            "phyGuardCutRate": 40.0,
            "magGuardCutRate": 10.0,
            "fireGuardCutRate": 30.0,
            "thunGuardCutRate": 30.0,
            "spEffectBehaviorId0": 6402,
            "spEffectBehaviorId1": -1,
            "spEffectBehaviorId2": -1,
            "residentSpEffectId": -1,
            "residentSpEffectId1": -1,
            "residentSpEffectId2": -1,
            "materialSetId": 800,
            "originEquipWep0": 1150005,
            "originEquipWep1": 1150005,
            "originEquipWep2": 1150005,
            "originEquipWep3": 1150005,
            "originEquipWep4": 1150005,
            "originEquipWep5": 1150005,
            "originEquipWep6": 1150805,
            "originEquipWep7": 1150805,
            "originEquipWep8": 1150805,
            "originEquipWep9": 1150805,
            "originEquipWep10": 1150805,
            "originEquipWep11": -1,
            "originEquipWep12": -1,
            "originEquipWep13": -1,
            "originEquipWep14": -1,
            "originEquipWep15": -1,
            "antiDemonDamageRate": 1.0,
            "antSaintDamageRate": 1.0,
            "antWeakA_DamageRate": 1.0,
            "antWeakB_DamageRate": 1.0,
            "vagrantItemLotId": 101000,
            "vagrantBonusEneDropItemLotId": 101010,
            "vagrantItemEneDropItemLotId": 101020,
            "equipModelId": 801,
            "iconId": 91,
            "durability": 130,
            "durabilityMax": 130,
            "attackThrowEscape": 1.0,
            "parryDamageLife": 10.0,
            "attackBasePhysics": 100.0,
            "attackBaseMagic": 0.0,
            "attackBaseFire": 100.0,
            "attackBaseThunder": 0.0,
            "attackBaseStamina": 25.0,
            "saWeaponDamage": 20.0,
            "saDurability": 0,
            "guardAngle": 0,
            "staminaGuardDef": 22,
            "reinforceTypeId": 800,
            "trophySGradeId": -1,
            "trophySeqId": 24,
            "throwAtkRate": 0.0,
            "bowDistRate": -1.0,
            "equipModelCategory": 7,
            "equipModelGender": 0,
            "weaponCategory": 7,
            "wepmotionCategory": 38,
            "guardmotionCategory": 2,
            "atkMaterial": 0,
            "defMaterial": 50,
            "defSfxMaterial": 50,
            "correctType": 0,
            "spAttribute": 2,
            "spAtkcategory": 50,
            "wepmotionOneHandId": 0,
            "wepmotionBothHandId": 13,
            "overStrength": 99.0,
            "attackBaseParry": 0.0,
            "defenseBaseParry": 0.0,
            "guardBaseRepel": 10.0,
            "attackBaseRepel": 40.0,
            "guardCutCancelRate": 0.0,
            "guardLevel": 2,
            "slashGuardCutRate": 0.0,
            "blowGuardCutRate": 0.0,
            "thrustGuardCutRate": 0.0,
            "poisonGuardResist": 36.0,
            "diseaseGuardResist": 36.0,
            "bloodGuardResist": 36.0,
            "curseGuardResist": 28.0,
            "isDurabilityDivergence": 0,
            "baseChangeCategory": 35,
            "pad_0": "System.Byte[]",
            "oldSortId": 1609,
            "pad_1": "System.Byte[]",
            "description": "Weapon type: Halberd\nAttack type: Slash\n\nWeapon with a long curved blade. Converted\nfrom a wheat-harvesting tool.\n\nThe magnificent sharp curved blade\ninstills fear in opponents. Perhaps it is\ntheir survival instinct at work.",
            "customData": {
                "whereToGet": "firelinkshrine",
                "slug": "Great-Scythe-[Fire]",
                "WeaponCategory": "Unknown",
                "WeaponType": "Slash",
                "image": "Great-Scythe-[Fire].png"
            }
        },
        {
            "Name": "Great Scythe [Chaos]",
            "Description": "Weapon type: Halberd\nAttack type: Slash\n\nWeapon with a long curved blade. Converted\nfrom a wheat-harvesting tool.\n\nThe magnificent sharp curved blade\ninstills fear in opponents. Perhaps it is\ntheir survival instinct at work.",
            "ID": 1150900,
            "sortId": 1610,
            "weight": 5.0,
            "basicPrice": 200,
            "sellValue": 50,
            "fixPrice": 260,
            "req": {
                "Required Strength": 50.0,
                "Required Dexterity": 0.0,
                "Required Magic": 13.0,
                "Required Faith": 14.0
            },
            "scale": {
                "Strength Scaling": 0.0,
                "Dexterity Scaling": 0.0,
                "Intelligence Scaling": 0.0,
                "Faith Scaling": 0.0
            },
            "boolFlags": {
                "rightHandEquippable": true,
                "leftHandEquippable": true,
                "bothHandEquippable": true,
                "arrowSlotEquippable": false,
                "boltSlotEquippable": false,
                "enableGuard": true,
                "enableParry": false,
                "enableMagic": false,
                "enableSorcery": false,
                "enableMiracle": false,
                "enableVowMagic": false,
                "isNormalAttackType": false,
                "isBlowAttackType": false,
                "isSlashAttackType": true,
                "isThrustAttackType": false,
                "isEnhance": false,
                "isLuckCorrect": true,
                "isCustom": true,
                "disableBaseChangeReset": false,
                "disableRepair": false,
                "isDarkHand": false,
                "simpleModelForDlc": false,
                "lanternWep": false,
                "isVersusGhostWep": false,
                "isDragonSlayer": false,
                "isDeposit": true,
                "disableMultiDropShare": false
            },
            "behaviorVariationId": 5000,
            "wanderingEquipId": 1199000,
            "weaponWeightRate": 0.0,
            "phyGuardCutRate": 40.0,
            "magGuardCutRate": 10.0,
            "fireGuardCutRate": 30.0,
            "thunGuardCutRate": 30.0,
            "spEffectBehaviorId0": 6402,
            "spEffectBehaviorId1": -1,
            "spEffectBehaviorId2": -1,
            "residentSpEffectId": -1,
            "residentSpEffectId1": -1,
            "residentSpEffectId2": -1,
            "materialSetId": 900,
            "originEquipWep0": 1150805,
            "originEquipWep1": 1150805,
            "originEquipWep2": 1150805,
            "originEquipWep3": 1150805,
            "originEquipWep4": 1150805,
            "originEquipWep5": 1150805,
            "originEquipWep6": -1,
            "originEquipWep7": -1,
            "originEquipWep8": -1,
            "originEquipWep9": -1,
            "originEquipWep10": -1,
            "originEquipWep11": -1,
            "originEquipWep12": -1,
            "originEquipWep13": -1,
            "originEquipWep14": -1,
            "originEquipWep15": -1,
            "antiDemonDamageRate": 1.0,
            "antSaintDamageRate": 1.0,
            "antWeakA_DamageRate": 1.0,
            "antWeakB_DamageRate": 1.0,
            "vagrantItemLotId": 101000,
            "vagrantBonusEneDropItemLotId": 101010,
            "vagrantItemEneDropItemLotId": 101020,
            "equipModelId": 801,
            "iconId": 91,
            "durability": 130,
            "durabilityMax": 130,
            "attackThrowEscape": 1.0,
            "parryDamageLife": 10.0,
            "attackBasePhysics": 87.0,
            "attackBaseMagic": 0.0,
            "attackBaseFire": 101.0,
            "attackBaseThunder": 0.0,
            "attackBaseStamina": 25.0,
            "saWeaponDamage": 20.0,
            "saDurability": 0,
            "guardAngle": 0,
            "staminaGuardDef": 22,
            "reinforceTypeId": 900,
            "trophySGradeId": -1,
            "trophySeqId": 25,
            "throwAtkRate": 0.0,
            "bowDistRate": -1.0,
            "equipModelCategory": 7,
            "equipModelGender": 0,
            "weaponCategory": 7,
            "wepmotionCategory": 38,
            "guardmotionCategory": 2,
            "atkMaterial": 0,
            "defMaterial": 50,
            "defSfxMaterial": 50,
            "correctType": 0,
            "spAttribute": 2,
            "spAtkcategory": 50,
            "wepmotionOneHandId": 0,
            "wepmotionBothHandId": 13,
            "overStrength": 99.0,
            "attackBaseParry": 0.0,
            "defenseBaseParry": 0.0,
            "guardBaseRepel": 10.0,
            "attackBaseRepel": 40.0,
            "guardCutCancelRate": 0.0,
            "guardLevel": 2,
            "slashGuardCutRate": 0.0,
            "blowGuardCutRate": 0.0,
            "thrustGuardCutRate": 0.0,
            "poisonGuardResist": 36.0,
            "diseaseGuardResist": 36.0,
            "bloodGuardResist": 36.0,
            "curseGuardResist": 28.0,
            "isDurabilityDivergence": 0,
            "baseChangeCategory": 40,
            "pad_0": "System.Byte[]",
            "oldSortId": 1610,
            "pad_1": "System.Byte[]",
            "description": "Weapon type: Halberd\nAttack type: Slash\n\nWeapon with a long curved blade. Converted\nfrom a wheat-harvesting tool.\n\nThe magnificent sharp curved blade\ninstills fear in opponents. Perhaps it is\ntheir survival instinct at work.",
            "customData": {
                "whereToGet": "firelinkshrine",
                "slug": "Great-Scythe-[Chaos]",
                "WeaponCategory": "Unknown",
                "WeaponType": "Slash",
                "image": "Great-Scythe-[Chaos].png"
            }
        }
    ]
}