{
    "Name": "Gargoyle Tail Axe",
    "Description": "Weapon type: Axe\nAttack type: Regular\n\nSliced tail of the gargoyle guarding the\nBell of Awakening in the Undead Church\nor patrolling in Anor Londo.\n\nCan be used as a bronze battle axe.\nBends dramatically during large attacks,\nowing to its nature as a tail.",
    "ID": 705000,
    "sortId": 1031,
    "weight": 5.0,
    "basicPrice": 200,
    "sellValue": 50,
    "fixPrice": 300,
    "req": {
        "Required Strength": 125.0,
        "Required Dexterity": 0.0,
        "Required Magic": 10.0,
        "Required Faith": 14.0
    },
    "scale": {
        "Strength Scaling": 22.0,
        "Dexterity Scaling": 70.0,
        "Intelligence Scaling": 0.0,
        "Faith Scaling": 0.0
    },
    "boolFlags": {
        "rightHandEquippable": true,
        "leftHandEquippable": true,
        "bothHandEquippable": true,
        "arrowSlotEquippable": false,
        "boltSlotEquippable": false,
        "enableGuard": true,
        "enableParry": false,
        "enableMagic": false,
        "enableSorcery": false,
        "enableMiracle": false,
        "enableVowMagic": false,
        "isNormalAttackType": true,
        "isBlowAttackType": false,
        "isSlashAttackType": false,
        "isThrustAttackType": false,
        "isEnhance": true,
        "isLuckCorrect": false,
        "isCustom": true,
        "disableBaseChangeReset": false,
        "disableRepair": false,
        "isDarkHand": false,
        "simpleModelForDlc": false,
        "lanternWep": false,
        "isVersusGhostWep": false,
        "isDragonSlayer": false,
        "isDeposit": true,
        "disableMultiDropShare": false
    },
    "behaviorVariationId": 3004,
    "wanderingEquipId": 798000,
    "weaponWeightRate": 0.0,
    "phyGuardCutRate": 55.0,
    "magGuardCutRate": 10.0,
    "fireGuardCutRate": 40.0,
    "thunGuardCutRate": 40.0,
    "spEffectBehaviorId0": -1,
    "spEffectBehaviorId1": -1,
    "spEffectBehaviorId2": -1,
    "residentSpEffectId": 6840,
    "residentSpEffectId1": -1,
    "residentSpEffectId2": -1,
    "materialSetId": 0,
    "originEquipWep0": 705000,
    "originEquipWep1": 705000,
    "originEquipWep2": 705000,
    "originEquipWep3": 705000,
    "originEquipWep4": 705000,
    "originEquipWep5": 705000,
    "originEquipWep6": 705005,
    "originEquipWep7": 705005,
    "originEquipWep8": 705005,
    "originEquipWep9": 705005,
    "originEquipWep10": 705005,
    "originEquipWep11": 705010,
    "originEquipWep12": 705010,
    "originEquipWep13": 705010,
    "originEquipWep14": 705010,
    "originEquipWep15": 705010,
    "antiDemonDamageRate": 1.0,
    "antSaintDamageRate": 1.0,
    "antWeakA_DamageRate": 1.0,
    "antWeakB_DamageRate": 1.0,
    "vagrantItemLotId": 100700,
    "vagrantBonusEneDropItemLotId": 100710,
    "vagrantItemEneDropItemLotId": 100720,
    "equipModelId": 509,
    "iconId": 166,
    "durability": 150,
    "durabilityMax": 150,
    "attackThrowEscape": 1.0,
    "parryDamageLife": 10.0,
    "attackBasePhysics": 93.0,
    "attackBaseMagic": 0.0,
    "attackBaseFire": 0.0,
    "attackBaseThunder": 0.0,
    "attackBaseStamina": 35.0,
    "saWeaponDamage": 35.0,
    "saDurability": 0,
    "guardAngle": 0,
    "staminaGuardDef": 36,
    "reinforceTypeId": 0,
    "trophySGradeId": -1,
    "trophySeqId": 16,
    "throwAtkRate": 0.0,
    "bowDistRate": -1.0,
    "equipModelCategory": 7,
    "equipModelGender": 0,
    "weaponCategory": 4,
    "wepmotionCategory": 30,
    "guardmotionCategory": 2,
    "atkMaterial": 0,
    "defMaterial": 50,
    "defSfxMaterial": 50,
    "correctType": 0,
    "spAttribute": 1,
    "spAtkcategory": 125,
    "wepmotionOneHandId": 0,
    "wepmotionBothHandId": 10,
    "overStrength": 99.0,
    "attackBaseParry": 0.0,
    "defenseBaseParry": 0.0,
    "guardBaseRepel": 10.0,
    "attackBaseRepel": 40.0,
    "guardCutCancelRate": 0.0,
    "guardLevel": 3,
    "slashGuardCutRate": 0.0,
    "blowGuardCutRate": 0.0,
    "thrustGuardCutRate": 0.0,
    "poisonGuardResist": 40.0,
    "diseaseGuardResist": 40.0,
    "bloodGuardResist": 40.0,
    "curseGuardResist": 42.0,
    "isDurabilityDivergence": 0,
    "baseChangeCategory": 0,
    "pad_0": "System.Byte[]",
    "oldSortId": 1031,
    "pad_1": "System.Byte[]",
    "description": "Weapon type: Axe\nAttack type: Regular\n\nSliced tail of the gargoyle guarding the\nBell of Awakening in the Undead Church\nor patrolling in Anor Londo.\n\nCan be used as a bronze battle axe.\nBends dramatically during large attacks,\nowing to its nature as a tail.",
    "customData": {
        "whereToGet": "firelinkshrine",
        "slug": "Gargoyle-Tail-Axe",
        "WeaponCategory": "Weapons",
        "WeaponType": "Slash",
        "image": "Gargoyle-Tail-Axe.png"
    },
    "variants": [
        {
            "Name": "Gargoyle Tail Axe [Crystal]",
            "Description": "Weapon type: Axe\nAttack type: Regular\n\nSliced tail of the gargoyle guarding the\nBell of Awakening in the Undead Church.\n\nCan be used as a bronze battle axe.\nBends dramatically during large attacks,\nowing to its nature as a tail.",
            "ID": 705100,
            "sortId": 1032,
            "weight": 5.0,
            "basicPrice": 200,
            "sellValue": 1,
            "fixPrice": 300,
            "req": {
                "Required Strength": 125.0,
                "Required Dexterity": 0.0,
                "Required Magic": 10.0,
                "Required Faith": 14.0
            },
            "scale": {
                "Strength Scaling": 22.0,
                "Dexterity Scaling": 70.0,
                "Intelligence Scaling": 0.0,
                "Faith Scaling": 0.0
            },
            "boolFlags": {
                "rightHandEquippable": true,
                "leftHandEquippable": true,
                "bothHandEquippable": true,
                "arrowSlotEquippable": false,
                "boltSlotEquippable": false,
                "enableGuard": true,
                "enableParry": false,
                "enableMagic": false,
                "enableSorcery": false,
                "enableMiracle": false,
                "enableVowMagic": false,
                "isNormalAttackType": true,
                "isBlowAttackType": false,
                "isSlashAttackType": false,
                "isThrustAttackType": false,
                "isEnhance": true,
                "isLuckCorrect": false,
                "isCustom": true,
                "disableBaseChangeReset": true,
                "disableRepair": true,
                "isDarkHand": false,
                "simpleModelForDlc": false,
                "lanternWep": false,
                "isVersusGhostWep": false,
                "isDragonSlayer": false,
                "isDeposit": true,
                "disableMultiDropShare": false
            },
            "behaviorVariationId": 3004,
            "wanderingEquipId": 798000,
            "weaponWeightRate": 0.0,
            "phyGuardCutRate": 55.0,
            "magGuardCutRate": 10.0,
            "fireGuardCutRate": 40.0,
            "thunGuardCutRate": 40.0,
            "spEffectBehaviorId0": -1,
            "spEffectBehaviorId1": -1,
            "spEffectBehaviorId2": -1,
            "residentSpEffectId": 6840,
            "residentSpEffectId1": -1,
            "residentSpEffectId2": -1,
            "materialSetId": 100,
            "originEquipWep0": 705010,
            "originEquipWep1": 705010,
            "originEquipWep2": 705010,
            "originEquipWep3": 705010,
            "originEquipWep4": 705010,
            "originEquipWep5": 705010,
            "originEquipWep6": -1,
            "originEquipWep7": -1,
            "originEquipWep8": -1,
            "originEquipWep9": -1,
            "originEquipWep10": -1,
            "originEquipWep11": -1,
            "originEquipWep12": -1,
            "originEquipWep13": -1,
            "originEquipWep14": -1,
            "originEquipWep15": -1,
            "antiDemonDamageRate": 1.0,
            "antSaintDamageRate": 1.0,
            "antWeakA_DamageRate": 1.0,
            "antWeakB_DamageRate": 1.0,
            "vagrantItemLotId": 100700,
            "vagrantBonusEneDropItemLotId": 100710,
            "vagrantItemEneDropItemLotId": 100720,
            "equipModelId": 509,
            "iconId": 166,
            "durability": 15,
            "durabilityMax": 15,
            "attackThrowEscape": 1.0,
            "parryDamageLife": 10.0,
            "attackBasePhysics": 93.0,
            "attackBaseMagic": 0.0,
            "attackBaseFire": 0.0,
            "attackBaseThunder": 0.0,
            "attackBaseStamina": 35.0,
            "saWeaponDamage": 35.0,
            "saDurability": 0,
            "guardAngle": 0,
            "staminaGuardDef": 36,
            "reinforceTypeId": 100,
            "trophySGradeId": -1,
            "trophySeqId": 17,
            "throwAtkRate": 0.0,
            "bowDistRate": -1.0,
            "equipModelCategory": 7,
            "equipModelGender": 0,
            "weaponCategory": 4,
            "wepmotionCategory": 30,
            "guardmotionCategory": 2,
            "atkMaterial": 0,
            "defMaterial": 50,
            "defSfxMaterial": 50,
            "correctType": 0,
            "spAttribute": 1,
            "spAtkcategory": 125,
            "wepmotionOneHandId": 0,
            "wepmotionBothHandId": 10,
            "overStrength": 99.0,
            "attackBaseParry": 0.0,
            "defenseBaseParry": 0.0,
            "guardBaseRepel": 10.0,
            "attackBaseRepel": 40.0,
            "guardCutCancelRate": 0.0,
            "guardLevel": 3,
            "slashGuardCutRate": 0.0,
            "blowGuardCutRate": 0.0,
            "thrustGuardCutRate": 0.0,
            "poisonGuardResist": 40.0,
            "diseaseGuardResist": 40.0,
            "bloodGuardResist": 40.0,
            "curseGuardResist": 42.0,
            "isDurabilityDivergence": 0,
            "baseChangeCategory": 5,
            "pad_0": "System.Byte[]",
            "oldSortId": 1032,
            "pad_1": "System.Byte[]",
            "description": "Weapon type: Axe\nAttack type: Regular\n\nSliced tail of the gargoyle guarding the\nBell of Awakening in the Undead Church.\n\nCan be used as a bronze battle axe.\nBends dramatically during large attacks,\nowing to its nature as a tail.",
            "customData": {
                "whereToGet": "firelinkshrine",
                "slug": "Gargoyle-Tail-Axe-[Crystal]",
                "WeaponCategory": "Unknown",
                "WeaponType": "Slash",
                "image": "Gargoyle-Tail-Axe-[Crystal].png"
            }
        },
        {
            "Name": "Gargoyle Tail Axe [Lightning]",
            "Description": "Weapon type: Axe\nAttack type: Regular\n\nSliced tail of the gargoyle guarding the\nBell of Awakening in the Undead Church.\n\nCan be used as a bronze battle axe.\nBends dramatically during large attacks,\nowing to its nature as a tail.",
            "ID": 705200,
            "sortId": 1033,
            "weight": 5.0,
            "basicPrice": 200,
            "sellValue": 500,
            "fixPrice": 300,
            "req": {
                "Required Strength": 125.0,
                "Required Dexterity": 0.0,
                "Required Magic": 10.0,
                "Required Faith": 14.0
            },
            "scale": {
                "Strength Scaling": 0.0,
                "Dexterity Scaling": 0.0,
                "Intelligence Scaling": 0.0,
                "Faith Scaling": 0.0
            },
            "boolFlags": {
                "rightHandEquippable": true,
                "leftHandEquippable": true,
                "bothHandEquippable": true,
                "arrowSlotEquippable": false,
                "boltSlotEquippable": false,
                "enableGuard": true,
                "enableParry": false,
                "enableMagic": false,
                "enableSorcery": false,
                "enableMiracle": false,
                "enableVowMagic": false,
                "isNormalAttackType": true,
                "isBlowAttackType": false,
                "isSlashAttackType": false,
                "isThrustAttackType": false,
                "isEnhance": false,
                "isLuckCorrect": false,
                "isCustom": true,
                "disableBaseChangeReset": false,
                "disableRepair": false,
                "isDarkHand": false,
                "simpleModelForDlc": false,
                "lanternWep": false,
                "isVersusGhostWep": false,
                "isDragonSlayer": false,
                "isDeposit": true,
                "disableMultiDropShare": false
            },
            "behaviorVariationId": 3004,
            "wanderingEquipId": 798000,
            "weaponWeightRate": 0.0,
            "phyGuardCutRate": 55.0,
            "magGuardCutRate": 10.0,
            "fireGuardCutRate": 40.0,
            "thunGuardCutRate": 40.0,
            "spEffectBehaviorId0": -1,
            "spEffectBehaviorId1": -1,
            "spEffectBehaviorId2": -1,
            "residentSpEffectId": 6840,
            "residentSpEffectId1": -1,
            "residentSpEffectId2": -1,
            "materialSetId": 200,
            "originEquipWep0": 705010,
            "originEquipWep1": 705010,
            "originEquipWep2": 705010,
            "originEquipWep3": 705010,
            "originEquipWep4": 705010,
            "originEquipWep5": 705010,
            "originEquipWep6": -1,
            "originEquipWep7": -1,
            "originEquipWep8": -1,
            "originEquipWep9": -1,
            "originEquipWep10": -1,
            "originEquipWep11": -1,
            "originEquipWep12": -1,
            "originEquipWep13": -1,
            "originEquipWep14": -1,
            "originEquipWep15": -1,
            "antiDemonDamageRate": 1.0,
            "antSaintDamageRate": 1.0,
            "antWeakA_DamageRate": 1.0,
            "antWeakB_DamageRate": 1.0,
            "vagrantItemLotId": 100700,
            "vagrantBonusEneDropItemLotId": 100710,
            "vagrantItemEneDropItemLotId": 100720,
            "equipModelId": 509,
            "iconId": 166,
            "durability": 150,
            "durabilityMax": 150,
            "attackThrowEscape": 1.0,
            "parryDamageLife": 10.0,
            "attackBasePhysics": 93.0,
            "attackBaseMagic": 0.0,
            "attackBaseFire": 0.0,
            "attackBaseThunder": 93.0,
            "attackBaseStamina": 35.0,
            "saWeaponDamage": 35.0,
            "saDurability": 0,
            "guardAngle": 0,
            "staminaGuardDef": 36,
            "reinforceTypeId": 200,
            "trophySGradeId": -1,
            "trophySeqId": 18,
            "throwAtkRate": 0.0,
            "bowDistRate": -1.0,
            "equipModelCategory": 7,
            "equipModelGender": 0,
            "weaponCategory": 4,
            "wepmotionCategory": 30,
            "guardmotionCategory": 2,
            "atkMaterial": 0,
            "defMaterial": 50,
            "defSfxMaterial": 50,
            "correctType": 0,
            "spAttribute": 6,
            "spAtkcategory": 125,
            "wepmotionOneHandId": 0,
            "wepmotionBothHandId": 10,
            "overStrength": 99.0,
            "attackBaseParry": 0.0,
            "defenseBaseParry": 0.0,
            "guardBaseRepel": 10.0,
            "attackBaseRepel": 40.0,
            "guardCutCancelRate": 0.0,
            "guardLevel": 3,
            "slashGuardCutRate": 0.0,
            "blowGuardCutRate": 0.0,
            "thrustGuardCutRate": 0.0,
            "poisonGuardResist": 40.0,
            "diseaseGuardResist": 40.0,
            "bloodGuardResist": 40.0,
            "curseGuardResist": 42.0,
            "isDurabilityDivergence": 0,
            "baseChangeCategory": 10,
            "pad_0": "System.Byte[]",
            "oldSortId": 1033,
            "pad_1": "System.Byte[]",
            "description": "Weapon type: Axe\nAttack type: Regular\n\nSliced tail of the gargoyle guarding the\nBell of Awakening in the Undead Church.\n\nCan be used as a bronze battle axe.\nBends dramatically during large attacks,\nowing to its nature as a tail.",
            "customData": {
                "whereToGet": "firelinkshrine",
                "slug": "Gargoyle-Tail-Axe-[Lightning]",
                "WeaponCategory": "Unknown",
                "WeaponType": "Slash",
                "image": "Gargoyle-Tail-Axe-[Lightning].png"
            }
        },
        {
            "Name": "Gargoyle Tail Axe [Raw]",
            "Description": "Weapon type: Axe\nAttack type: Regular\n\nSliced tail of the gargoyle guarding the\nBell of Awakening in the Undead Church.\n\nCan be used as a bronze battle axe.\nBends dramatically during large attacks,\nowing to its nature as a tail.",
            "ID": 705300,
            "sortId": 1034,
            "weight": 5.0,
            "basicPrice": 200,
            "sellValue": 50,
            "fixPrice": 300,
            "req": {
                "Required Strength": 125.0,
                "Required Dexterity": 0.0,
                "Required Magic": 10.0,
                "Required Faith": 14.0
            },
            "scale": {
                "Strength Scaling": 17.0,
                "Dexterity Scaling": 53.0,
                "Intelligence Scaling": 0.0,
                "Faith Scaling": 0.0
            },
            "boolFlags": {
                "rightHandEquippable": true,
                "leftHandEquippable": true,
                "bothHandEquippable": true,
                "arrowSlotEquippable": false,
                "boltSlotEquippable": false,
                "enableGuard": true,
                "enableParry": false,
                "enableMagic": false,
                "enableSorcery": false,
                "enableMiracle": false,
                "enableVowMagic": false,
                "isNormalAttackType": true,
                "isBlowAttackType": false,
                "isSlashAttackType": false,
                "isThrustAttackType": false,
                "isEnhance": true,
                "isLuckCorrect": false,
                "isCustom": true,
                "disableBaseChangeReset": false,
                "disableRepair": false,
                "isDarkHand": false,
                "simpleModelForDlc": false,
                "lanternWep": false,
                "isVersusGhostWep": false,
                "isDragonSlayer": false,
                "isDeposit": true,
                "disableMultiDropShare": false
            },
            "behaviorVariationId": 3004,
            "wanderingEquipId": 798000,
            "weaponWeightRate": 0.0,
            "phyGuardCutRate": 55.0,
            "magGuardCutRate": 10.0,
            "fireGuardCutRate": 40.0,
            "thunGuardCutRate": 40.0,
            "spEffectBehaviorId0": -1,
            "spEffectBehaviorId1": -1,
            "spEffectBehaviorId2": -1,
            "residentSpEffectId": 6840,
            "residentSpEffectId1": -1,
            "residentSpEffectId2": -1,
            "materialSetId": 300,
            "originEquipWep0": 705005,
            "originEquipWep1": 705005,
            "originEquipWep2": 705005,
            "originEquipWep3": 705005,
            "originEquipWep4": 705005,
            "originEquipWep5": 705005,
            "originEquipWep6": -1,
            "originEquipWep7": -1,
            "originEquipWep8": -1,
            "originEquipWep9": -1,
            "originEquipWep10": -1,
            "originEquipWep11": -1,
            "originEquipWep12": -1,
            "originEquipWep13": -1,
            "originEquipWep14": -1,
            "originEquipWep15": -1,
            "antiDemonDamageRate": 1.0,
            "antSaintDamageRate": 1.0,
            "antWeakA_DamageRate": 1.0,
            "antWeakB_DamageRate": 1.0,
            "vagrantItemLotId": -1,
            "vagrantBonusEneDropItemLotId": -1,
            "vagrantItemEneDropItemLotId": -1,
            "equipModelId": 509,
            "iconId": 166,
            "durability": 150,
            "durabilityMax": 150,
            "attackThrowEscape": 1.0,
            "parryDamageLife": 10.0,
            "attackBasePhysics": 107.0,
            "attackBaseMagic": 0.0,
            "attackBaseFire": 0.0,
            "attackBaseThunder": 0.0,
            "attackBaseStamina": 35.0,
            "saWeaponDamage": 35.0,
            "saDurability": 0,
            "guardAngle": 0,
            "staminaGuardDef": 36,
            "reinforceTypeId": 300,
            "trophySGradeId": -1,
            "trophySeqId": 19,
            "throwAtkRate": 0.0,
            "bowDistRate": -1.0,
            "equipModelCategory": 7,
            "equipModelGender": 0,
            "weaponCategory": 4,
            "wepmotionCategory": 30,
            "guardmotionCategory": 2,
            "atkMaterial": 0,
            "defMaterial": 50,
            "defSfxMaterial": 50,
            "correctType": 0,
            "spAttribute": 1,
            "spAtkcategory": 125,
            "wepmotionOneHandId": 0,
            "wepmotionBothHandId": 10,
            "overStrength": 99.0,
            "attackBaseParry": 0.0,
            "defenseBaseParry": 0.0,
            "guardBaseRepel": 10.0,
            "attackBaseRepel": 40.0,
            "guardCutCancelRate": 0.0,
            "guardLevel": 3,
            "slashGuardCutRate": 0.0,
            "blowGuardCutRate": 0.0,
            "thrustGuardCutRate": 0.0,
            "poisonGuardResist": 40.0,
            "diseaseGuardResist": 40.0,
            "bloodGuardResist": 40.0,
            "curseGuardResist": 42.0,
            "isDurabilityDivergence": 0,
            "baseChangeCategory": 15,
            "pad_0": "System.Byte[]",
            "oldSortId": 1034,
            "pad_1": "System.Byte[]",
            "description": "Weapon type: Axe\nAttack type: Regular\n\nSliced tail of the gargoyle guarding the\nBell of Awakening in the Undead Church.\n\nCan be used as a bronze battle axe.\nBends dramatically during large attacks,\nowing to its nature as a tail.",
            "customData": {
                "whereToGet": "firelinkshrine",
                "slug": "Gargoyle-Tail-Axe-[Raw]",
                "WeaponCategory": "Unknown",
                "WeaponType": "Slash",
                "image": "Gargoyle-Tail-Axe-[Raw].png"
            }
        },
        {
            "Name": "Gargoyle Tail Axe [Magic]",
            "Description": "Weapon type: Axe\nAttack type: Regular\n\nSliced tail of the gargoyle guarding the\nBell of Awakening in the Undead Church.\n\nCan be used as a bronze battle axe.\nBends dramatically during large attacks,\nowing to its nature as a tail.",
            "ID": 705400,
            "sortId": 1035,
            "weight": 5.0,
            "basicPrice": 200,
            "sellValue": 50,
            "fixPrice": 300,
            "req": {
                "Required Strength": 125.0,
                "Required Dexterity": 0.0,
                "Required Magic": 10.0,
                "Required Faith": 14.0
            },
            "scale": {
                "Strength Scaling": 6.0,
                "Dexterity Scaling": 20.0,
                "Intelligence Scaling": 66.0,
                "Faith Scaling": 0.0
            },
            "boolFlags": {
                "rightHandEquippable": true,
                "leftHandEquippable": true,
                "bothHandEquippable": true,
                "arrowSlotEquippable": false,
                "boltSlotEquippable": false,
                "enableGuard": true,
                "enableParry": false,
                "enableMagic": false,
                "enableSorcery": false,
                "enableMiracle": false,
                "enableVowMagic": false,
                "isNormalAttackType": true,
                "isBlowAttackType": false,
                "isSlashAttackType": false,
                "isThrustAttackType": false,
                "isEnhance": false,
                "isLuckCorrect": false,
                "isCustom": true,
                "disableBaseChangeReset": false,
                "disableRepair": false,
                "isDarkHand": false,
                "simpleModelForDlc": false,
                "lanternWep": false,
                "isVersusGhostWep": false,
                "isDragonSlayer": false,
                "isDeposit": true,
                "disableMultiDropShare": false
            },
            "behaviorVariationId": 3004,
            "wanderingEquipId": 798000,
            "weaponWeightRate": 0.0,
            "phyGuardCutRate": 55.0,
            "magGuardCutRate": 10.0,
            "fireGuardCutRate": 40.0,
            "thunGuardCutRate": 40.0,
            "spEffectBehaviorId0": -1,
            "spEffectBehaviorId1": -1,
            "spEffectBehaviorId2": -1,
            "residentSpEffectId": 6840,
            "residentSpEffectId1": -1,
            "residentSpEffectId2": -1,
            "materialSetId": 400,
            "originEquipWep0": 705005,
            "originEquipWep1": 705005,
            "originEquipWep2": 705005,
            "originEquipWep3": 705005,
            "originEquipWep4": 705005,
            "originEquipWep5": 705005,
            "originEquipWep6": 705405,
            "originEquipWep7": 705405,
            "originEquipWep8": 705405,
            "originEquipWep9": 705405,
            "originEquipWep10": 705405,
            "originEquipWep11": -1,
            "originEquipWep12": -1,
            "originEquipWep13": -1,
            "originEquipWep14": -1,
            "originEquipWep15": -1,
            "antiDemonDamageRate": 1.0,
            "antSaintDamageRate": 1.0,
            "antWeakA_DamageRate": 1.0,
            "antWeakB_DamageRate": 1.0,
            "vagrantItemLotId": 100800,
            "vagrantBonusEneDropItemLotId": 100810,
            "vagrantItemEneDropItemLotId": 100820,
            "equipModelId": 509,
            "iconId": 166,
            "durability": 150,
            "durabilityMax": 150,
            "attackThrowEscape": 1.0,
            "parryDamageLife": 10.0,
            "attackBasePhysics": 70.0,
            "attackBaseMagic": 76.0,
            "attackBaseFire": 0.0,
            "attackBaseThunder": 0.0,
            "attackBaseStamina": 35.0,
            "saWeaponDamage": 35.0,
            "saDurability": 0,
            "guardAngle": 0,
            "staminaGuardDef": 36,
            "reinforceTypeId": 400,
            "trophySGradeId": -1,
            "trophySeqId": 20,
            "throwAtkRate": 0.0,
            "bowDistRate": -1.0,
            "equipModelCategory": 7,
            "equipModelGender": 0,
            "weaponCategory": 4,
            "wepmotionCategory": 30,
            "guardmotionCategory": 2,
            "atkMaterial": 0,
            "defMaterial": 50,
            "defSfxMaterial": 50,
            "correctType": 1,
            "spAttribute": 1,
            "spAtkcategory": 125,
            "wepmotionOneHandId": 0,
            "wepmotionBothHandId": 10,
            "overStrength": 99.0,
            "attackBaseParry": 0.0,
            "defenseBaseParry": 0.0,
            "guardBaseRepel": 10.0,
            "attackBaseRepel": 40.0,
            "guardCutCancelRate": 0.0,
            "guardLevel": 3,
            "slashGuardCutRate": 0.0,
            "blowGuardCutRate": 0.0,
            "thrustGuardCutRate": 0.0,
            "poisonGuardResist": 40.0,
            "diseaseGuardResist": 40.0,
            "bloodGuardResist": 40.0,
            "curseGuardResist": 42.0,
            "isDurabilityDivergence": 0,
            "baseChangeCategory": 20,
            "pad_0": "System.Byte[]",
            "oldSortId": 1035,
            "pad_1": "System.Byte[]",
            "description": "Weapon type: Axe\nAttack type: Regular\n\nSliced tail of the gargoyle guarding the\nBell of Awakening in the Undead Church.\n\nCan be used as a bronze battle axe.\nBends dramatically during large attacks,\nowing to its nature as a tail.",
            "customData": {
                "whereToGet": "firelinkshrine",
                "slug": "Gargoyle-Tail-Axe-[Magic]",
                "WeaponCategory": "Unknown",
                "WeaponType": "Slash",
                "image": "Gargoyle-Tail-Axe-[Magic].png"
            }
        },
        {
            "Name": "Gargoyle Tail Axe [Enchanted]",
            "Description": "Weapon type: Axe\nAttack type: Regular\n\nSliced tail of the gargoyle guarding the\nBell of Awakening in the Undead Church.\n\nCan be used as a bronze battle axe.\nBends dramatically during large attacks,\nowing to its nature as a tail.",
            "ID": 705500,
            "sortId": 1036,
            "weight": 5.0,
            "basicPrice": 200,
            "sellValue": 50,
            "fixPrice": 300,
            "req": {
                "Required Strength": 125.0,
                "Required Dexterity": 0.0,
                "Required Magic": 10.0,
                "Required Faith": 14.0
            },
            "scale": {
                "Strength Scaling": 4.0,
                "Dexterity Scaling": 14.0,
                "Intelligence Scaling": 65.0,
                "Faith Scaling": 0.0
            },
            "boolFlags": {
                "rightHandEquippable": true,
                "leftHandEquippable": true,
                "bothHandEquippable": true,
                "arrowSlotEquippable": false,
                "boltSlotEquippable": false,
                "enableGuard": true,
                "enableParry": false,
                "enableMagic": false,
                "enableSorcery": false,
                "enableMiracle": false,
                "enableVowMagic": false,
                "isNormalAttackType": true,
                "isBlowAttackType": false,
                "isSlashAttackType": false,
                "isThrustAttackType": false,
                "isEnhance": false,
                "isLuckCorrect": false,
                "isCustom": true,
                "disableBaseChangeReset": false,
                "disableRepair": false,
                "isDarkHand": false,
                "simpleModelForDlc": false,
                "lanternWep": false,
                "isVersusGhostWep": false,
                "isDragonSlayer": false,
                "isDeposit": true,
                "disableMultiDropShare": false
            },
            "behaviorVariationId": 3004,
            "wanderingEquipId": 798000,
            "weaponWeightRate": 0.0,
            "phyGuardCutRate": 55.0,
            "magGuardCutRate": 10.0,
            "fireGuardCutRate": 40.0,
            "thunGuardCutRate": 40.0,
            "spEffectBehaviorId0": -1,
            "spEffectBehaviorId1": -1,
            "spEffectBehaviorId2": -1,
            "residentSpEffectId": 6840,
            "residentSpEffectId1": -1,
            "residentSpEffectId2": -1,
            "materialSetId": 500,
            "originEquipWep0": 705405,
            "originEquipWep1": 705405,
            "originEquipWep2": 705405,
            "originEquipWep3": 705405,
            "originEquipWep4": 705405,
            "originEquipWep5": 705405,
            "originEquipWep6": -1,
            "originEquipWep7": -1,
            "originEquipWep8": -1,
            "originEquipWep9": -1,
            "originEquipWep10": -1,
            "originEquipWep11": -1,
            "originEquipWep12": -1,
            "originEquipWep13": -1,
            "originEquipWep14": -1,
            "originEquipWep15": -1,
            "antiDemonDamageRate": 1.0,
            "antSaintDamageRate": 1.0,
            "antWeakA_DamageRate": 1.0,
            "antWeakB_DamageRate": 1.0,
            "vagrantItemLotId": 100800,
            "vagrantBonusEneDropItemLotId": 100810,
            "vagrantItemEneDropItemLotId": 100820,
            "equipModelId": 509,
            "iconId": 166,
            "durability": 150,
            "durabilityMax": 150,
            "attackThrowEscape": 1.0,
            "parryDamageLife": 10.0,
            "attackBasePhysics": 70.0,
            "attackBaseMagic": 74.0,
            "attackBaseFire": 0.0,
            "attackBaseThunder": 0.0,
            "attackBaseStamina": 35.0,
            "saWeaponDamage": 35.0,
            "saDurability": 0,
            "guardAngle": 0,
            "staminaGuardDef": 36,
            "reinforceTypeId": 500,
            "trophySGradeId": -1,
            "trophySeqId": 21,
            "throwAtkRate": 0.0,
            "bowDistRate": -1.0,
            "equipModelCategory": 7,
            "equipModelGender": 0,
            "weaponCategory": 4,
            "wepmotionCategory": 30,
            "guardmotionCategory": 2,
            "atkMaterial": 0,
            "defMaterial": 50,
            "defSfxMaterial": 50,
            "correctType": 1,
            "spAttribute": 1,
            "spAtkcategory": 125,
            "wepmotionOneHandId": 0,
            "wepmotionBothHandId": 10,
            "overStrength": 99.0,
            "attackBaseParry": 0.0,
            "defenseBaseParry": 0.0,
            "guardBaseRepel": 10.0,
            "attackBaseRepel": 40.0,
            "guardCutCancelRate": 0.0,
            "guardLevel": 3,
            "slashGuardCutRate": 0.0,
            "blowGuardCutRate": 0.0,
            "thrustGuardCutRate": 0.0,
            "poisonGuardResist": 40.0,
            "diseaseGuardResist": 40.0,
            "bloodGuardResist": 40.0,
            "curseGuardResist": 42.0,
            "isDurabilityDivergence": 0,
            "baseChangeCategory": 22,
            "pad_0": "System.Byte[]",
            "oldSortId": 1036,
            "pad_1": "System.Byte[]",
            "description": "Weapon type: Axe\nAttack type: Regular\n\nSliced tail of the gargoyle guarding the\nBell of Awakening in the Undead Church.\n\nCan be used as a bronze battle axe.\nBends dramatically during large attacks,\nowing to its nature as a tail.",
            "customData": {
                "whereToGet": "firelinkshrine",
                "slug": "Gargoyle-Tail-Axe-[Enchanted]",
                "WeaponCategory": "Unknown",
                "WeaponType": "Slash",
                "image": "Gargoyle-Tail-Axe-[Enchanted].png"
            }
        },
        {
            "Name": "Gargoyle Tail Axe [Divine]",
            "Description": "Weapon type: Axe\nAttack type: Regular\n\nSliced tail of the gargoyle guarding the\nBell of Awakening in the Undead Church.\n\nCan be used as a bronze battle axe.\nBends dramatically during large attacks,\nowing to its nature as a tail.",
            "ID": 705600,
            "sortId": 1037,
            "weight": 5.0,
            "basicPrice": 200,
            "sellValue": 100,
            "fixPrice": 300,
            "req": {
                "Required Strength": 125.0,
                "Required Dexterity": 0.0,
                "Required Magic": 10.0,
                "Required Faith": 14.0
            },
            "scale": {
                "Strength Scaling": 8.0,
                "Dexterity Scaling": 27.0,
                "Intelligence Scaling": 0.0,
                "Faith Scaling": 66.0
            },
            "boolFlags": {
                "rightHandEquippable": true,
                "leftHandEquippable": true,
                "bothHandEquippable": true,
                "arrowSlotEquippable": false,
                "boltSlotEquippable": false,
                "enableGuard": true,
                "enableParry": false,
                "enableMagic": false,
                "enableSorcery": false,
                "enableMiracle": false,
                "enableVowMagic": false,
                "isNormalAttackType": true,
                "isBlowAttackType": false,
                "isSlashAttackType": false,
                "isThrustAttackType": false,
                "isEnhance": false,
                "isLuckCorrect": false,
                "isCustom": true,
                "disableBaseChangeReset": false,
                "disableRepair": false,
                "isDarkHand": false,
                "simpleModelForDlc": false,
                "lanternWep": false,
                "isVersusGhostWep": false,
                "isDragonSlayer": false,
                "isDeposit": true,
                "disableMultiDropShare": false
            },
            "behaviorVariationId": 3004,
            "wanderingEquipId": 798000,
            "weaponWeightRate": 0.0,
            "phyGuardCutRate": 55.0,
            "magGuardCutRate": 10.0,
            "fireGuardCutRate": 40.0,
            "thunGuardCutRate": 40.0,
            "spEffectBehaviorId0": -1,
            "spEffectBehaviorId1": -1,
            "spEffectBehaviorId2": -1,
            "residentSpEffectId": 6840,
            "residentSpEffectId1": -1,
            "residentSpEffectId2": -1,
            "materialSetId": 600,
            "originEquipWep0": 705005,
            "originEquipWep1": 705005,
            "originEquipWep2": 705005,
            "originEquipWep3": 705005,
            "originEquipWep4": 705005,
            "originEquipWep5": 705005,
            "originEquipWep6": 705605,
            "originEquipWep7": 705605,
            "originEquipWep8": 705605,
            "originEquipWep9": 705605,
            "originEquipWep10": 705605,
            "originEquipWep11": -1,
            "originEquipWep12": -1,
            "originEquipWep13": -1,
            "originEquipWep14": -1,
            "originEquipWep15": -1,
            "antiDemonDamageRate": 1.0,
            "antSaintDamageRate": 1.1,
            "antWeakA_DamageRate": 1.0,
            "antWeakB_DamageRate": 1.0,
            "vagrantItemLotId": 100900,
            "vagrantBonusEneDropItemLotId": 100910,
            "vagrantItemEneDropItemLotId": 100920,
            "equipModelId": 509,
            "iconId": 166,
            "durability": 150,
            "durabilityMax": 150,
            "attackThrowEscape": 1.0,
            "parryDamageLife": 10.0,
            "attackBasePhysics": 63.0,
            "attackBaseMagic": 77.0,
            "attackBaseFire": 0.0,
            "attackBaseThunder": 0.0,
            "attackBaseStamina": 35.0,
            "saWeaponDamage": 35.0,
            "saDurability": 0,
            "guardAngle": 0,
            "staminaGuardDef": 36,
            "reinforceTypeId": 600,
            "trophySGradeId": -1,
            "trophySeqId": 22,
            "throwAtkRate": 0.0,
            "bowDistRate": -1.0,
            "equipModelCategory": 7,
            "equipModelGender": 0,
            "weaponCategory": 4,
            "wepmotionCategory": 30,
            "guardmotionCategory": 2,
            "atkMaterial": 0,
            "defMaterial": 50,
            "defSfxMaterial": 50,
            "correctType": 1,
            "spAttribute": 1,
            "spAtkcategory": 125,
            "wepmotionOneHandId": 0,
            "wepmotionBothHandId": 10,
            "overStrength": 99.0,
            "attackBaseParry": 0.0,
            "defenseBaseParry": 0.0,
            "guardBaseRepel": 10.0,
            "attackBaseRepel": 40.0,
            "guardCutCancelRate": 0.0,
            "guardLevel": 3,
            "slashGuardCutRate": 0.0,
            "blowGuardCutRate": 0.0,
            "thrustGuardCutRate": 0.0,
            "poisonGuardResist": 40.0,
            "diseaseGuardResist": 40.0,
            "bloodGuardResist": 40.0,
            "curseGuardResist": 42.0,
            "isDurabilityDivergence": 0,
            "baseChangeCategory": 25,
            "pad_0": "System.Byte[]",
            "oldSortId": 1037,
            "pad_1": "System.Byte[]",
            "description": "Weapon type: Axe\nAttack type: Regular\n\nSliced tail of the gargoyle guarding the\nBell of Awakening in the Undead Church.\n\nCan be used as a bronze battle axe.\nBends dramatically during large attacks,\nowing to its nature as a tail.",
            "customData": {
                "whereToGet": "firelinkshrine",
                "slug": "Gargoyle-Tail-Axe-[Divine]",
                "WeaponCategory": "Unknown",
                "WeaponType": "Slash",
                "image": "Gargoyle-Tail-Axe-[Divine].png"
            }
        },
        {
            "Name": "Gargoyle Tail Axe [Occult]",
            "Description": "Weapon type: Axe\nAttack type: Regular\n\nSliced tail of the gargoyle guarding the\nBell of Awakening in the Undead Church.\n\nCan be used as a bronze battle axe.\nBends dramatically during large attacks,\nowing to its nature as a tail.",
            "ID": 705700,
            "sortId": 1038,
            "weight": 5.0,
            "basicPrice": 200,
            "sellValue": 100,
            "fixPrice": 300,
            "req": {
                "Required Strength": 125.0,
                "Required Dexterity": 0.0,
                "Required Magic": 10.0,
                "Required Faith": 14.0
            },
            "scale": {
                "Strength Scaling": 8.0,
                "Dexterity Scaling": 25.0,
                "Intelligence Scaling": 0.0,
                "Faith Scaling": 77.0
            },
            "boolFlags": {
                "rightHandEquippable": true,
                "leftHandEquippable": true,
                "bothHandEquippable": true,
                "arrowSlotEquippable": false,
                "boltSlotEquippable": false,
                "enableGuard": true,
                "enableParry": false,
                "enableMagic": false,
                "enableSorcery": false,
                "enableMiracle": false,
                "enableVowMagic": false,
                "isNormalAttackType": true,
                "isBlowAttackType": false,
                "isSlashAttackType": false,
                "isThrustAttackType": false,
                "isEnhance": false,
                "isLuckCorrect": false,
                "isCustom": true,
                "disableBaseChangeReset": false,
                "disableRepair": false,
                "isDarkHand": false,
                "simpleModelForDlc": false,
                "lanternWep": false,
                "isVersusGhostWep": false,
                "isDragonSlayer": false,
                "isDeposit": true,
                "disableMultiDropShare": false
            },
            "behaviorVariationId": 3004,
            "wanderingEquipId": 798000,
            "weaponWeightRate": 0.0,
            "phyGuardCutRate": 55.0,
            "magGuardCutRate": 10.0,
            "fireGuardCutRate": 40.0,
            "thunGuardCutRate": 40.0,
            "spEffectBehaviorId0": -1,
            "spEffectBehaviorId1": -1,
            "spEffectBehaviorId2": -1,
            "residentSpEffectId": 6840,
            "residentSpEffectId1": -1,
            "residentSpEffectId2": -1,
            "materialSetId": 700,
            "originEquipWep0": 705605,
            "originEquipWep1": 705605,
            "originEquipWep2": 705605,
            "originEquipWep3": 705605,
            "originEquipWep4": 705605,
            "originEquipWep5": 705605,
            "originEquipWep6": -1,
            "originEquipWep7": -1,
            "originEquipWep8": -1,
            "originEquipWep9": -1,
            "originEquipWep10": -1,
            "originEquipWep11": -1,
            "originEquipWep12": -1,
            "originEquipWep13": -1,
            "originEquipWep14": -1,
            "originEquipWep15": -1,
            "antiDemonDamageRate": 1.0,
            "antSaintDamageRate": 1.0,
            "antWeakA_DamageRate": 1.1,
            "antWeakB_DamageRate": 1.0,
            "vagrantItemLotId": 100900,
            "vagrantBonusEneDropItemLotId": 100910,
            "vagrantItemEneDropItemLotId": 100920,
            "equipModelId": 509,
            "iconId": 166,
            "durability": 150,
            "durabilityMax": 150,
            "attackThrowEscape": 1.0,
            "parryDamageLife": 10.0,
            "attackBasePhysics": 64.0,
            "attackBaseMagic": 70.0,
            "attackBaseFire": 0.0,
            "attackBaseThunder": 0.0,
            "attackBaseStamina": 35.0,
            "saWeaponDamage": 35.0,
            "saDurability": 0,
            "guardAngle": 0,
            "staminaGuardDef": 36,
            "reinforceTypeId": 700,
            "trophySGradeId": -1,
            "trophySeqId": 23,
            "throwAtkRate": 0.0,
            "bowDistRate": -1.0,
            "equipModelCategory": 7,
            "equipModelGender": 0,
            "weaponCategory": 4,
            "wepmotionCategory": 30,
            "guardmotionCategory": 2,
            "atkMaterial": 0,
            "defMaterial": 50,
            "defSfxMaterial": 50,
            "correctType": 1,
            "spAttribute": 1,
            "spAtkcategory": 125,
            "wepmotionOneHandId": 0,
            "wepmotionBothHandId": 10,
            "overStrength": 99.0,
            "attackBaseParry": 0.0,
            "defenseBaseParry": 0.0,
            "guardBaseRepel": 10.0,
            "attackBaseRepel": 40.0,
            "guardCutCancelRate": 0.0,
            "guardLevel": 3,
            "slashGuardCutRate": 0.0,
            "blowGuardCutRate": 0.0,
            "thrustGuardCutRate": 0.0,
            "poisonGuardResist": 40.0,
            "diseaseGuardResist": 40.0,
            "bloodGuardResist": 40.0,
            "curseGuardResist": 42.0,
            "isDurabilityDivergence": 0,
            "baseChangeCategory": 30,
            "pad_0": "System.Byte[]",
            "oldSortId": 1038,
            "pad_1": "System.Byte[]",
            "description": "Weapon type: Axe\nAttack type: Regular\n\nSliced tail of the gargoyle guarding the\nBell of Awakening in the Undead Church.\n\nCan be used as a bronze battle axe.\nBends dramatically during large attacks,\nowing to its nature as a tail.",
            "customData": {
                "whereToGet": "firelinkshrine",
                "slug": "Gargoyle-Tail-Axe-[Occult]",
                "WeaponCategory": "Unknown",
                "WeaponType": "Slash",
                "image": "Gargoyle-Tail-Axe-[Occult].png"
            }
        },
        {
            "Name": "Gargoyle Tail Axe [Fire]",
            "Description": "Weapon type: Axe\nAttack type: Regular\n\nSliced tail of the gargoyle guarding the\nBell of Awakening in the Undead Church.\n\nCan be used as a bronze battle axe.\nBends dramatically during large attacks,\nowing to its nature as a tail.",
            "ID": 705800,
            "sortId": 1039,
            "weight": 5.0,
            "basicPrice": 200,
            "sellValue": 50,
            "fixPrice": 300,
            "req": {
                "Required Strength": 125.0,
                "Required Dexterity": 0.0,
                "Required Magic": 10.0,
                "Required Faith": 14.0
            },
            "scale": {
                "Strength Scaling": 0.0,
                "Dexterity Scaling": 0.0,
                "Intelligence Scaling": 0.0,
                "Faith Scaling": 0.0
            },
            "boolFlags": {
                "rightHandEquippable": true,
                "leftHandEquippable": true,
                "bothHandEquippable": true,
                "arrowSlotEquippable": false,
                "boltSlotEquippable": false,
                "enableGuard": true,
                "enableParry": false,
                "enableMagic": false,
                "enableSorcery": false,
                "enableMiracle": false,
                "enableVowMagic": false,
                "isNormalAttackType": true,
                "isBlowAttackType": false,
                "isSlashAttackType": false,
                "isThrustAttackType": false,
                "isEnhance": false,
                "isLuckCorrect": false,
                "isCustom": true,
                "disableBaseChangeReset": false,
                "disableRepair": false,
                "isDarkHand": false,
                "simpleModelForDlc": false,
                "lanternWep": false,
                "isVersusGhostWep": false,
                "isDragonSlayer": false,
                "isDeposit": true,
                "disableMultiDropShare": false
            },
            "behaviorVariationId": 3004,
            "wanderingEquipId": 798000,
            "weaponWeightRate": 0.0,
            "phyGuardCutRate": 55.0,
            "magGuardCutRate": 10.0,
            "fireGuardCutRate": 40.0,
            "thunGuardCutRate": 40.0,
            "spEffectBehaviorId0": -1,
            "spEffectBehaviorId1": -1,
            "spEffectBehaviorId2": -1,
            "residentSpEffectId": 6840,
            "residentSpEffectId1": -1,
            "residentSpEffectId2": -1,
            "materialSetId": 800,
            "originEquipWep0": 705005,
            "originEquipWep1": 705005,
            "originEquipWep2": 705005,
            "originEquipWep3": 705005,
            "originEquipWep4": 705005,
            "originEquipWep5": 705005,
            "originEquipWep6": 705805,
            "originEquipWep7": 705805,
            "originEquipWep8": 705805,
            "originEquipWep9": 705805,
            "originEquipWep10": 705805,
            "originEquipWep11": -1,
            "originEquipWep12": -1,
            "originEquipWep13": -1,
            "originEquipWep14": -1,
            "originEquipWep15": -1,
            "antiDemonDamageRate": 1.0,
            "antSaintDamageRate": 1.0,
            "antWeakA_DamageRate": 1.0,
            "antWeakB_DamageRate": 1.0,
            "vagrantItemLotId": 101000,
            "vagrantBonusEneDropItemLotId": 101010,
            "vagrantItemEneDropItemLotId": 101020,
            "equipModelId": 509,
            "iconId": 166,
            "durability": 150,
            "durabilityMax": 150,
            "attackThrowEscape": 1.0,
            "parryDamageLife": 10.0,
            "attackBasePhysics": 93.0,
            "attackBaseMagic": 0.0,
            "attackBaseFire": 93.0,
            "attackBaseThunder": 0.0,
            "attackBaseStamina": 35.0,
            "saWeaponDamage": 35.0,
            "saDurability": 0,
            "guardAngle": 0,
            "staminaGuardDef": 36,
            "reinforceTypeId": 800,
            "trophySGradeId": -1,
            "trophySeqId": 24,
            "throwAtkRate": 0.0,
            "bowDistRate": -1.0,
            "equipModelCategory": 7,
            "equipModelGender": 0,
            "weaponCategory": 4,
            "wepmotionCategory": 30,
            "guardmotionCategory": 2,
            "atkMaterial": 0,
            "defMaterial": 50,
            "defSfxMaterial": 50,
            "correctType": 0,
            "spAttribute": 2,
            "spAtkcategory": 125,
            "wepmotionOneHandId": 0,
            "wepmotionBothHandId": 10,
            "overStrength": 99.0,
            "attackBaseParry": 0.0,
            "defenseBaseParry": 0.0,
            "guardBaseRepel": 10.0,
            "attackBaseRepel": 40.0,
            "guardCutCancelRate": 0.0,
            "guardLevel": 3,
            "slashGuardCutRate": 0.0,
            "blowGuardCutRate": 0.0,
            "thrustGuardCutRate": 0.0,
            "poisonGuardResist": 40.0,
            "diseaseGuardResist": 40.0,
            "bloodGuardResist": 40.0,
            "curseGuardResist": 42.0,
            "isDurabilityDivergence": 0,
            "baseChangeCategory": 35,
            "pad_0": "System.Byte[]",
            "oldSortId": 1039,
            "pad_1": "System.Byte[]",
            "description": "Weapon type: Axe\nAttack type: Regular\n\nSliced tail of the gargoyle guarding the\nBell of Awakening in the Undead Church.\n\nCan be used as a bronze battle axe.\nBends dramatically during large attacks,\nowing to its nature as a tail.",
            "customData": {
                "whereToGet": "firelinkshrine",
                "slug": "Gargoyle-Tail-Axe-[Fire]",
                "WeaponCategory": "Unknown",
                "WeaponType": "Slash",
                "image": "Gargoyle-Tail-Axe-[Fire].png"
            }
        },
        {
            "Name": "Gargoyle Tail Axe [Chaos]",
            "Description": "Weapon type: Axe\nAttack type: Regular\n\nSliced tail of the gargoyle guarding the\nBell of Awakening in the Undead Church.\n\nCan be used as a bronze battle axe.\nBends dramatically during large attacks,\nowing to its nature as a tail.",
            "ID": 705900,
            "sortId": 1040,
            "weight": 5.0,
            "basicPrice": 200,
            "sellValue": 50,
            "fixPrice": 300,
            "req": {
                "Required Strength": 125.0,
                "Required Dexterity": 0.0,
                "Required Magic": 10.0,
                "Required Faith": 14.0
            },
            "scale": {
                "Strength Scaling": 0.0,
                "Dexterity Scaling": 0.0,
                "Intelligence Scaling": 0.0,
                "Faith Scaling": 0.0
            },
            "boolFlags": {
                "rightHandEquippable": true,
                "leftHandEquippable": true,
                "bothHandEquippable": true,
                "arrowSlotEquippable": false,
                "boltSlotEquippable": false,
                "enableGuard": true,
                "enableParry": false,
                "enableMagic": false,
                "enableSorcery": false,
                "enableMiracle": false,
                "enableVowMagic": false,
                "isNormalAttackType": true,
                "isBlowAttackType": false,
                "isSlashAttackType": false,
                "isThrustAttackType": false,
                "isEnhance": false,
                "isLuckCorrect": true,
                "isCustom": true,
                "disableBaseChangeReset": false,
                "disableRepair": false,
                "isDarkHand": false,
                "simpleModelForDlc": false,
                "lanternWep": false,
                "isVersusGhostWep": false,
                "isDragonSlayer": false,
                "isDeposit": true,
                "disableMultiDropShare": false
            },
            "behaviorVariationId": 3004,
            "wanderingEquipId": 798000,
            "weaponWeightRate": 0.0,
            "phyGuardCutRate": 55.0,
            "magGuardCutRate": 10.0,
            "fireGuardCutRate": 40.0,
            "thunGuardCutRate": 40.0,
            "spEffectBehaviorId0": -1,
            "spEffectBehaviorId1": -1,
            "spEffectBehaviorId2": -1,
            "residentSpEffectId": 6840,
            "residentSpEffectId1": -1,
            "residentSpEffectId2": -1,
            "materialSetId": 900,
            "originEquipWep0": 705805,
            "originEquipWep1": 705805,
            "originEquipWep2": 705805,
            "originEquipWep3": 705805,
            "originEquipWep4": 705805,
            "originEquipWep5": 705805,
            "originEquipWep6": -1,
            "originEquipWep7": -1,
            "originEquipWep8": -1,
            "originEquipWep9": -1,
            "originEquipWep10": -1,
            "originEquipWep11": -1,
            "originEquipWep12": -1,
            "originEquipWep13": -1,
            "originEquipWep14": -1,
            "originEquipWep15": -1,
            "antiDemonDamageRate": 1.0,
            "antSaintDamageRate": 1.0,
            "antWeakA_DamageRate": 1.0,
            "antWeakB_DamageRate": 1.0,
            "vagrantItemLotId": 101000,
            "vagrantBonusEneDropItemLotId": 101010,
            "vagrantItemEneDropItemLotId": 101020,
            "equipModelId": 509,
            "iconId": 166,
            "durability": 150,
            "durabilityMax": 150,
            "attackThrowEscape": 1.0,
            "parryDamageLife": 10.0,
            "attackBasePhysics": 81.0,
            "attackBaseMagic": 0.0,
            "attackBaseFire": 93.0,
            "attackBaseThunder": 0.0,
            "attackBaseStamina": 35.0,
            "saWeaponDamage": 35.0,
            "saDurability": 0,
            "guardAngle": 0,
            "staminaGuardDef": 36,
            "reinforceTypeId": 900,
            "trophySGradeId": -1,
            "trophySeqId": 25,
            "throwAtkRate": 0.0,
            "bowDistRate": -1.0,
            "equipModelCategory": 7,
            "equipModelGender": 0,
            "weaponCategory": 4,
            "wepmotionCategory": 30,
            "guardmotionCategory": 2,
            "atkMaterial": 0,
            "defMaterial": 50,
            "defSfxMaterial": 50,
            "correctType": 0,
            "spAttribute": 2,
            "spAtkcategory": 125,
            "wepmotionOneHandId": 0,
            "wepmotionBothHandId": 10,
            "overStrength": 99.0,
            "attackBaseParry": 0.0,
            "defenseBaseParry": 0.0,
            "guardBaseRepel": 10.0,
            "attackBaseRepel": 40.0,
            "guardCutCancelRate": 0.0,
            "guardLevel": 3,
            "slashGuardCutRate": 0.0,
            "blowGuardCutRate": 0.0,
            "thrustGuardCutRate": 0.0,
            "poisonGuardResist": 40.0,
            "diseaseGuardResist": 40.0,
            "bloodGuardResist": 40.0,
            "curseGuardResist": 42.0,
            "isDurabilityDivergence": 0,
            "baseChangeCategory": 40,
            "pad_0": "System.Byte[]",
            "oldSortId": 1040,
            "pad_1": "System.Byte[]",
            "description": "Weapon type: Axe\nAttack type: Regular\n\nSliced tail of the gargoyle guarding the\nBell of Awakening in the Undead Church.\n\nCan be used as a bronze battle axe.\nBends dramatically during large attacks,\nowing to its nature as a tail.",
            "customData": {
                "whereToGet": "firelinkshrine",
                "slug": "Gargoyle-Tail-Axe-[Chaos]",
                "WeaponCategory": "Unknown",
                "WeaponType": "Slash",
                "image": "Gargoyle-Tail-Axe-[Chaos].png"
            }
        }
    ]
}